{"nodes":[{"kind":"decl","code":".motherboard #p18296 {","children":[{"kind":"decl","code":"--ci:","children":[{"kind":"value","code":"mod(var(--__1mc336828), 256);"}]},{"kind":"block","code":"background-color: --screenPx(var(--vidMode), var(--ci), mod(var(--__1mc382055), 256), var(--__1mc377119), var(--__1mc377406), 1, 128, 128, var(--vidPal));"}],"trailer":"}","folded":true},{"kind":"decl","code":".motherboard #p18297 {","children":[{"kind":"decl","code":"--ci:","children":[{"kind":"value","code":"round(down, var(--__1mc336828) / 256);"}]},{"kind":"block","code":"background-color: --screenPx(var(--vidMode), var(--ci), mod(var(--__1mc382055), 256), var(--__1mc377119), var(--__1mc377406), 1, 64, 32, var(--vidPal));"}],"trailer":"}","folded":true},{"kind":"decl","code":".motherboard #p18298 {","children":[{"kind":"decl","code":"--ci:","children":[{"kind":"value","code":"mod(var(--__1mc336829), 256);"}]},{"kind":"block","code":"background-color: --screenPx(var(--vidMode), var(--ci), mod(var(--__1mc382055), 256), var(--__1mc377119), var(--__1mc377406), 1, 32, 8, var(--vidPal));"}],"trailer":"}","folded":true},{"kind":"decl","code":".motherboard #p18299 {","children":[{"kind":"decl","code":"--ci:","children":[{"kind":"value","code":"round(down, var(--__1mc336829) / 256);"}]},{"kind":"block","code":"background-color: --screenPx(var(--vidMode), var(--ci), mod(var(--__1mc382055), 256), var(--__1mc377119), var(--__1mc377406), 1, 16, 2, var(--vidPal));"}],"trailer":"}","folded":true},{"kind":"decl","code":".motherboard #p18300 {","children":[{"kind":"decl","code":"--ci:","children":[{"kind":"value","code":"mod(var(--__1mc336830), 256);"}]},{"kind":"block","code":"background-color: --screenPx(var(--vidMode), var(--ci), round(down, var(--__1mc382055) / 256), var(--__1mc377119), var(--__1mc377407), 1, 8, 128, var(--vidPal));"}],"trailer":"}","folded":true},{"kind":"decl","code":".motherboard #p18301 {","children":[{"kind":"decl","code":"--ci:","children":[{"kind":"value","code":"round(down, var(--__1mc336830) / 256);"}]},{"kind":"block","code":"background-color: --screenPx(var(--vidMode), var(--ci), round(down, var(--__1mc382055) / 256), var(--__1mc377119), var(--__1mc377407), 1, 4, 32, var(--vidPal));"}],"trailer":"}","folded":true},{"kind":"decl","code":".motherboard #p18302 {","children":[{"kind":"decl","code":"--ci:","children":[{"kind":"value","code":"mod(var(--__1mc336831), 256);"}]},{"kind":"block","code":"background-color: --screenPx(var(--vidMode), var(--ci), round(down, var(--__1mc382055) / 256), var(--__1mc377119), var(--__1mc377407), 1, 2, 8, var(--vidPal));"}],"trailer":"}","folded":true},{"kind":"decl","code":".motherboard #p18303 {","children":[{"kind":"decl","code":"--ci:","children":[{"kind":"value","code":"round(down, var(--__1mc336831) / 256);"}]},{"kind":"block","code":"background-color: --screenPx(var(--vidMode), var(--ci), round(down, var(--__1mc382055) / 256), var(--__1mc377119), var(--__1mc377407), 1, 1, 2, var(--vidPal));"}],"trailer":"}","folded":true},{"kind":"decl","code":".motherboard #p18304 {","children":[{"kind":"decl","code":"--ci:","children":[{"kind":"value","code":"mod(var(--__1mc336832), 256);"}]},{"kind":"block","code":"background-color: --screenPx(var(--vidMode), var(--ci), mod(var(--__1mc382056), 256), var(--__1mc377120), var(--__1mc377408), 1, 128, 128, var(--vidPal));"}],"trailer":"}","folded":true},{"kind":"decl","code":".motherboard #p18305 {","children":[{"kind":"decl","code":"--ci:","children":[{"kind":"value","code":"round(down, var(--__1mc336832) / 256);"}]},{"kind":"block","code":"background-color: --screenPx(var(--vidMode), var(--ci), mod(var(--__1mc382056), 256), var(--__1mc377120), var(--__1mc377408), 1, 64, 32, var(--vidPal));"}],"trailer":"}","folded":true},{"kind":"decl","code":".motherboard #p18306 {","children":[{"kind":"decl","code":"--ci:","children":[{"kind":"value","code":"mod(var(--__1mc336833), 256);"}]},{"kind":"block","code":"background-color: --screenPx(var(--vidMode), var(--ci), mod(var(--__1mc382056), 256), var(--__1mc377120), var(--__1mc377408), 1, 32, 8, var(--vidPal));"}],"trailer":"}","folded":true},{"kind":"decl","code":".motherboard #p18307 {","children":[{"kind":"decl","code":"--ci:","children":[{"kind":"value","code":"round(down, var(--__1mc336833) / 256);"}]},{"kind":"block","code":"background-color: --screenPx(var(--vidMode), var(--ci), mod(var(--__1mc382056), 256), var(--__1mc377120), var(--__1mc377408), 1, 16, 2, var(--vidPal));"}],"trailer":"}","folded":true},{"kind":"decl","code":".motherboard #p18308 {","children":[{"kind":"decl","code":"--ci:","children":[{"kind":"value","code":"mod(var(--__1mc336834), 256);"}]},{"kind":"block","code":"background-color: --screenPx(var(--vidMode), var(--ci), round(down, var(--__1mc382056) / 256), var(--__1mc377120), var(--__1mc377409), 1, 8, 128, var(--vidPal));"}],"trailer":"}","folded":true},{"kind":"decl","code":".motherboard #p18309 {","children":[{"kind":"decl","code":"--ci:","children":[{"kind":"value","code":"round(down, var(--__1mc336834) / 256);"}]},{"kind":"block","code":"background-color: --screenPx(var(--vidMode), var(--ci), round(down, var(--__1mc382056) / 256), var(--__1mc377120), var(--__1mc377409), 1, 4, 32, var(--vidPal));"}],"trailer":"}","folded":true},{"kind":"decl","code":".motherboard #p18310 {","children":[{"kind":"decl","code":"--ci:","children":[{"kind":"value","code":"mod(var(--__1mc336835), 256);"}]},{"kind":"block","code":"background-color: --screenPx(var(--vidMode), var(--ci), round(down, var(--__1mc382056) / 256), var(--__1mc377120), var(--__1mc377409), 1, 2, 8, var(--vidPal));"}],"trailer":"}","folded":true},{"kind":"decl","code":".motherboard #p18311 {","children":[{"kind":"decl","code":"--ci:","children":[{"kind":"value","code":"round(down, var(--__1mc336835) / 256);"}]},{"kind":"block","code":"background-color: --screenPx(var(--vidMode), var(--ci), round(down, var(--__1mc382056) / 256), var(--__1mc377120), var(--__1mc377409), 1, 1, 2, var(--vidPal));"}],"trailer":"}","folded":true},{"kind":"decl","code":".motherboard #p18312 {","children":[{"kind":"decl","code":"--ci:","children":[{"kind":"value","code":"mod(var(--__1mc336836), 256);"}]},{"kind":"block","code":"background-color: --screenPx(var(--vidMode), var(--ci), mod(var(--__1mc382057), 256), var(--__1mc377121), var(--__1mc377410), 1, 128, 128, var(--vidPal));"}],"trailer":"}","folded":true},{"kind":"decl","code":".motherboard #p18313 {","children":[{"kind":"decl","code":"--ci:","children":[{"kind":"value","code":"round(down, var(--__1mc336836) / 256);"}]},{"kind":"block","code":"background-color: --screenPx(var(--vidMode), var(--ci), mod(var(--__1mc382057), 256), var(--__1mc377121), var(--__1mc377410), 1, 64, 32, var(--vidPal));"}],"trailer":"}","folded":true},{"kind":"decl","code":".motherboard #p18314 {","children":[{"kind":"decl","code":"--ci:","children":[{"kind":"value","code":"mod(var(--__1mc336837), 256);"}]},{"kind":"block","code":"background-color: --screenPx(var(--vidMode), var(--ci), mod(var(--__1mc382057), 256), var(--__1mc377121), var(--__1mc377410), 1, 32, 8, var(--vidPal));"}],"trailer":"}","folded":true},{"kind":"decl","code":".motherboard #p18315 {","children":[{"kind":"decl","code":"--ci:","children":[{"kind":"value","code":"round(down, var(--__1mc336837) / 256);"}]},{"kind":"block","code":"background-color: --screenPx(var(--vidMode), var(--ci), mod(var(--__1mc382057), 256), var(--__1mc377121), var(--__1mc377410), 1, 16, 2, var(--vidPal));"}],"trailer":"}","folded":true},{"kind":"decl","code":".motherboard #p18316 {","children":[{"kind":"decl","code":"--ci:","children":[{"kind":"value","code":"mod(var(--__1mc336838), 256);"}]},{"kind":"block","code":"background-color: --screenPx(var(--vidMode), var(--ci), round(down, var(--__1mc382057) / 256), var(--__1mc377121), var(--__1mc377411), 1, 8, 128, var(--vidPal));"}],"trailer":"}","folded":true},{"kind":"decl","code":".motherboard #p18317 {","children":[{"kind":"decl","code":"--ci:","children":[{"kind":"value","code":"round(down, var(--__1mc336838) / 256);"}]},{"kind":"block","code":"background-color: --screenPx(var(--vidMode), var(--ci), round(down, var(--__1mc382057) / 256), var(--__1mc377121), var(--__1mc377411), 1, 4, 32, var(--vidPal));"}],"trailer":"}","folded":true},{"kind":"decl","code":".motherboard #p18318 {","children":[{"kind":"decl","code":"--ci:","children":[{"kind":"value","code":"mod(var(--__1mc336839), 256);"}]},{"kind":"block","code":"background-color: --screenPx(var(--vidMode), var(--ci), round(down, var(--__1mc382057) / 256), var(--__1mc377121), var(--__1mc377411), 1, 2, 8, var(--vidPal));"}],"trailer":"}","folded":true},{"kind":"decl","code":".motherboard #p18319 {","children":[{"kind":"decl","code":"--ci:","children":[{"kind":"value","code":"round(down, var(--__1mc336839) / 256);"}]},{"kind":"block","code":"background-color: --screenPx(var(--vidMode), var(--ci), round(down, var(--__1mc382057) / 256), var(--__1mc377121), var(--__1mc377411), 1, 1, 2, var(--vidPal));"}],"trailer":"}","folded":true},{"kind":"decl","code":".motherboard #p18320 {","children":[{"kind":"decl","code":"--ci:","children":[{"kind":"value","code":"mod(var(--__1mc336840), 256);"}]},{"kind":"block","code":"background-color: --screenPx(var(--vidMode), var(--ci), mod(var(--__1mc382058), 256), var(--__1mc377122), var(--__1mc377412), 1, 128, 128, var(--vidPal));"}],"trailer":"}","folded":true},{"kind":"decl","code":".motherboard #p18321 {","children":[{"kind":"decl","code":"--ci:","children":[{"kind":"value","code":"round(down, var(--__1mc336840) / 256);"}]},{"kind":"block","code":"background-color: --screenPx(var(--vidMode), var(--ci), mod(var(--__1mc382058), 256), var(--__1mc377122), var(--__1mc377412), 1, 64, 32, var(--vidPal));"}],"trailer":"}","folded":true},{"kind":"decl","code":".motherboard #p18322 {","children":[{"kind":"decl","code":"--ci:","children":[{"kind":"value","code":"mod(var(--__1mc336841), 256);"}]},{"kind":"block","code":"background-color: --screenPx(var(--vidMode), var(--ci), mod(var(--__1mc382058), 256), var(--__1mc377122), var(--__1mc377412), 1, 32, 8, var(--vidPal));"}],"trailer":"}","folded":true},{"kind":"decl","code":".motherboard #p18323 {","children":[{"kind":"decl","code":"--ci:","children":[{"kind":"value","code":"round(down, var(--__1mc336841) / 256);"}]},{"kind":"block","code":"background-color: --screenPx(var(--vidMode), var(--ci), mod(var(--__1mc382058), 256), var(--__1mc377122), var(--__1mc377412), 1, 16, 2, var(--vidPal));"}],"trailer":"}","folded":true},{"kind":"decl","code":".motherboard #p18324 {","children":[{"kind":"decl","code":"--ci:","children":[{"kind":"value","code":"mod(var(--__1mc336842), 256);"}]},{"kind":"block","code":"background-color: --screenPx(var(--vidMode), var(--ci), round(down, var(--__1mc382058) / 256), var(--__1mc377122), var(--__1mc377413), 1, 8, 128, var(--vidPal));"}],"trailer":"}","folded":true},{"kind":"decl","code":".motherboard #p18325 {","children":[{"kind":"decl","code":"--ci:","children":[{"kind":"value","code":"round(down, var(--__1mc336842) / 256);"}]},{"kind":"block","code":"background-color: --screenPx(var(--vidMode), var(--ci), round(down, var(--__1mc382058) / 256), var(--__1mc377122), var(--__1mc377413), 1, 4, 32, var(--vidPal));"}],"trailer":"}","folded":true},{"kind":"decl","code":".motherboard #p18326 {","children":[{"kind":"decl","code":"--ci:","children":[{"kind":"value","code":"mod(var(--__1mc336843), 256);"}]},{"kind":"block","code":"background-color: --screenPx(var(--vidMode), var(--ci), round(down, var(--__1mc382058) / 256), var(--__1mc377122), var(--__1mc377413), 1, 2, 8, var(--vidPal));"}],"trailer":"}","folded":true},{"kind":"decl","code":".motherboard #p18327 {","children":[{"kind":"decl","code":"--ci:","children":[{"kind":"value","code":"round(down, var(--__1mc336843) / 256);"}]},{"kind":"block","code":"background-color: --screenPx(var(--vidMode), var(--ci), round(down, var(--__1mc382058) / 256), var(--__1mc377122), var(--__1mc377413), 1, 1, 2, var(--vidPal));"}],"trailer":"}","folded":true},{"kind":"decl","code":".motherboard #p18328 {","children":[{"kind":"decl","code":"--ci:","children":[{"kind":"value","code":"mod(var(--__1mc336844), 256);"}]},{"kind":"block","code":"background-color: --screenPx(var(--vidMode), var(--ci), mod(var(--__1mc382059), 256), var(--__1mc377123), var(--__1mc377414), 1, 128, 128, var(--vidPal));"}],"trailer":"}","folded":true},{"kind":"decl","code":".motherboard #p18329 {","children":[{"kind":"decl","code":"--ci:","children":[{"kind":"value","code":"round(down, var(--__1mc336844) / 256);"}]},{"kind":"block","code":"background-color: --screenPx(var(--vidMode), var(--ci), mod(var(--__1mc382059), 256), var(--__1mc377123), var(--__1mc377414), 1, 64, 32, var(--vidPal));"}],"trailer":"}","folded":true},{"kind":"decl","code":".motherboard #p18330 {","children":[{"kind":"decl","code":"--ci:","children":[{"kind":"value","code":"mod(var(--__1mc336845), 256);"}]},{"kind":"block","code":"background-color: --screenPx(var(--vidMode), var(--ci), mod(var(--__1mc382059), 256), var(--__1mc377123), var(--__1mc377414), 1, 32, 8, var(--vidPal));"}],"trailer":"}","folded":true},{"kind":"decl","code":".motherboard #p18331 {","children":[{"kind":"decl","code":"--ci:","children":[{"kind":"value","code":"round(down, var(--__1mc336845) / 256);"}]},{"kind":"block","code":"background-color: --screenPx(var(--vidMode), var(--ci), mod(var(--__1mc382059), 256), var(--__1mc377123), var(--__1mc377414), 1, 16, 2, var(--vidPal));"}],"trailer":"}","folded":true},{"kind":"decl","code":".motherboard #p18332 {","children":[{"kind":"decl","code":"--ci:","children":[{"kind":"value","code":"mod(var(--__1mc336846), 256);"}]},{"kind":"block","code":"background-color: --screenPx(var(--vidMode), var(--ci), round(down, var(--__1mc382059) / 256), var(--__1mc377123), var(--__1mc377415), 1, 8, 128, var(--vidPal));"}],"trailer":"}","folded":true},{"kind":"decl","code":".motherboard #p18333 {","children":[{"kind":"decl","code":"--ci:","children":[{"kind":"value","code":"round(down, var(--__1mc336846) / 256);"}]},{"kind":"block","code":"background-color: --screenPx(var(--vidMode), var(--ci), round(down, var(--__1mc382059) / 256), var(--__1mc377123), var(--__1mc377415), 1, 4, 32, var(--vidPal));"}],"trailer":"}","folded":true},{"kind":"decl","code":".motherboard #p18334 {","children":[{"kind":"decl","code":"--ci:","children":[{"kind":"value","code":"mod(var(--__1mc336847), 256);"}]},{"kind":"block","code":"background-color: --screenPx(var(--vidMode), var(--ci), round(down, var(--__1mc382059) / 256), var(--__1mc377123), var(--__1mc377415), 1, 2, 8, var(--vidPal));"}],"trailer":"}","folded":true},{"kind":"decl","code":".motherboard #p18335 {","children":[{"kind":"decl","code":"--ci:","children":[{"kind":"value","code":"round(down, var(--__1mc336847) / 256);"}]},{"kind":"block","code":"background-color: --screenPx(var(--vidMode), var(--ci), round(down, var(--__1mc382059) / 256), var(--__1mc377123), var(--__1mc377415), 1, 1, 2, var(--vidPal));"}],"trailer":"}","folded":true},{"kind":"decl","code":".motherboard #p18336 {","children":[{"kind":"decl","code":"--ci:","children":[{"kind":"value","code":"mod(var(--__1mc336848), 256);"}]},{"kind":"block","code":"background-color: --screenPx(var(--vidMode), var(--ci), mod(var(--__1mc382060), 256), var(--__1mc377124), var(--__1mc377416), 1, 128, 128, var(--vidPal));"}],"trailer":"}","folded":true},{"kind":"decl","code":".motherboard #p18337 {","children":[{"kind":"decl","code":"--ci:","children":[{"kind":"value","code":"round(down, var(--__1mc336848) / 256);"}]},{"kind":"block","code":"background-color: --screenPx(var(--vidMode), var(--ci), mod(var(--__1mc382060), 256), var(--__1mc377124), var(--__1mc377416), 1, 64, 32, var(--vidPal));"}],"trailer":"}","folded":true},{"kind":"decl","code":".motherboard #p18338 {","children":[{"kind":"decl","code":"--ci:","children":[{"kind":"value","code":"mod(var(--__1mc336849), 256);"}]},{"kind":"block","code":"background-color: --screenPx(var(--vidMode), var(--ci), mod(var(--__1mc382060), 256), var(--__1mc377124), var(--__1mc377416), 1, 32, 8, var(--vidPal));"}],"trailer":"}","folded":true},{"kind":"decl","code":".motherboard #p18339 {","children":[{"kind":"decl","code":"--ci:","children":[{"kind":"value","code":"round(down, var(--__1mc336849) / 256);"}]},{"kind":"block","code":"background-color: --screenPx(var(--vidMode), var(--ci), mod(var(--__1mc382060), 256), var(--__1mc377124), var(--__1mc377416), 1, 16, 2, var(--vidPal));"}],"trailer":"}","folded":true},{"kind":"decl","code":".motherboard #p18340 {","children":[{"kind":"decl","code":"--ci:","children":[{"kind":"value","code":"mod(var(--__1mc336850), 256);"}]},{"kind":"block","code":"background-color: --screenPx(var(--vidMode), var(--ci), round(down, var(--__1mc382060) / 256), var(--__1mc377124), var(--__1mc377417), 1, 8, 128, var(--vidPal));"}],"trailer":"}","folded":true},{"kind":"decl","code":".motherboard #p18341 {","children":[{"kind":"decl","code":"--ci:","children":[{"kind":"value","code":"round(down, var(--__1mc336850) / 256);"}]},{"kind":"block","code":"background-color: --screenPx(var(--vidMode), var(--ci), round(down, var(--__1mc382060) / 256), var(--__1mc377124), var(--__1mc377417), 1, 4, 32, var(--vidPal));"}],"trailer":"}","folded":true},{"kind":"decl","code":".motherboard #p18342 {","children":[{"kind":"decl","code":"--ci:","children":[{"kind":"value","code":"mod(var(--__1mc336851), 256);"}]},{"kind":"block","code":"background-color: --screenPx(var(--vidMode), var(--ci), round(down, var(--__1mc382060) / 256), var(--__1mc377124), var(--__1mc377417), 1, 2, 8, var(--vidPal));"}],"trailer":"}","folded":true},{"kind":"decl","code":".motherboard #p18343 {","children":[{"kind":"decl","code":"--ci:","children":[{"kind":"value","code":"round(down, var(--__1mc336851) / 256);"}]},{"kind":"block","code":"background-color: --screenPx(var(--vidMode), var(--ci), round(down, var(--__1mc382060) / 256), var(--__1mc377124), var(--__1mc377417), 1, 1, 2, var(--vidPal));"}],"trailer":"}","folded":true},{"kind":"decl","code":".motherboard #p18344 {","children":[{"kind":"decl","code":"--ci:","children":[{"kind":"value","code":"mod(var(--__1mc336852), 256);"}]},{"kind":"block","code":"background-color: --screenPx(var(--vidMode), var(--ci), mod(var(--__1mc382061), 256), var(--__1mc377125), var(--__1mc377418), 1, 128, 128, var(--vidPal));"}],"trailer":"}","folded":true},{"kind":"decl","code":".motherboard #p18345 {","children":[{"kind":"decl","code":"--ci:","children":[{"kind":"value","code":"round(down, var(--__1mc336852) / 256);"}]},{"kind":"block","code":"background-color: --screenPx(var(--vidMode), var(--ci), mod(var(--__1mc382061), 256), var(--__1mc377125), var(--__1mc377418), 1, 64, 32, var(--vidPal));"}],"trailer":"}","folded":true},{"kind":"decl","code":".motherboard #p18346 {","children":[{"kind":"decl","code":"--ci:","children":[{"kind":"value","code":"mod(var(--__1mc336853), 256);"}]},{"kind":"block","code":"background-color: --screenPx(var(--vidMode), var(--ci), mod(var(--__1mc382061), 256), var(--__1mc377125), var(--__1mc377418), 1, 32, 8, var(--vidPal));"}],"trailer":"}","folded":true},{"kind":"decl","code":".motherboard #p18347 {","children":[{"kind":"decl","code":"--ci:","children":[{"kind":"value","code":"round(down, var(--__1mc336853) / 256);"}]},{"kind":"block","code":"background-color: --screenPx(var(--vidMode), var(--ci), mod(var(--__1mc382061), 256), var(--__1mc377125), var(--__1mc377418), 1, 16, 2, var(--vidPal));"}],"trailer":"}","folded":true},{"kind":"decl","code":".motherboard #p18348 {","children":[{"kind":"decl","code":"--ci:","children":[{"kind":"value","code":"mod(var(--__1mc336854), 256);"}]},{"kind":"block","code":"background-color: --screenPx(var(--vidMode), var(--ci), round(down, var(--__1mc382061) / 256), var(--__1mc377125), var(--__1mc377419), 1, 8, 128, var(--vidPal));"}],"trailer":"}","folded":true},{"kind":"decl","code":".motherboard #p18349 {","children":[{"kind":"decl","code":"--ci:","children":[{"kind":"value","code":"round(down, var(--__1mc336854) / 256);"}]},{"kind":"block","code":"background-color: --screenPx(var(--vidMode), var(--ci), round(down, var(--__1mc382061) / 256), var(--__1mc377125), var(--__1mc377419), 1, 4, 32, var(--vidPal));"}],"trailer":"}","folded":true},{"kind":"decl","code":".motherboard #p18350 {","children":[{"kind":"decl","code":"--ci:","children":[{"kind":"value","code":"mod(var(--__1mc336855), 256);"}]},{"kind":"block","code":"background-color: --screenPx(var(--vidMode), var(--ci), round(down, var(--__1mc382061) / 256), var(--__1mc377125), var(--__1mc377419), 1, 2, 8, var(--vidPal));"}],"trailer":"}","folded":true},{"kind":"decl","code":".motherboard #p18351 {","children":[{"kind":"decl","code":"--ci:","children":[{"kind":"value","code":"round(down, var(--__1mc336855) / 256);"}]},{"kind":"block","code":"background-color: --screenPx(var(--vidMode), var(--ci), round(down, var(--__1mc382061) / 256), var(--__1mc377125), var(--__1mc377419), 1, 1, 2, var(--vidPal));"}],"trailer":"}","folded":true},{"kind":"decl","code":".motherboard #p18352 {","children":[{"kind":"decl","code":"--ci:","children":[{"kind":"value","code":"mod(var(--__1mc336856), 256);"}]},{"kind":"block","code":"background-color: --screenPx(var(--vidMode), var(--ci), mod(var(--__1mc382062), 256), var(--__1mc377126), var(--__1mc377420), 1, 128, 128, var(--vidPal));"}],"trailer":"}","folded":true},{"kind":"decl","code":".motherboard #p18353 {","children":[{"kind":"decl","code":"--ci:","children":[{"kind":"value","code":"round(down, var(--__1mc336856) / 256);"}]},{"kind":"block","code":"background-color: --screenPx(var(--vidMode), var(--ci), mod(var(--__1mc382062), 256), var(--__1mc377126), var(--__1mc377420), 1, 64, 32, var(--vidPal));"}],"trailer":"}","folded":true},{"kind":"decl","code":".motherboard #p18354 {","children":[{"kind":"decl","code":"--ci:","children":[{"kind":"value","code":"mod(var(--__1mc336857), 256);"}]},{"kind":"block","code":"background-color: --screenPx(var(--vidMode), var(--ci), mod(var(--__1mc382062), 256), var(--__1mc377126), var(--__1mc377420), 1, 32, 8, var(--vidPal));"}],"trailer":"}","folded":true},{"kind":"decl","code":".motherboard #p18355 {","children":[{"kind":"decl","code":"--ci:","children":[{"kind":"value","code":"round(down, var(--__1mc336857) / 256);"}]},{"kind":"block","code":"background-color: --screenPx(var(--vidMode), var(--ci), mod(var(--__1mc382062), 256), var(--__1mc377126), var(--__1mc377420), 1, 16, 2, var(--vidPal));"}],"trailer":"}","folded":true},{"kind":"decl","code":".motherboard #p18356 {","children":[{"kind":"decl","code":"--ci:","children":[{"kind":"value","code":"mod(var(--__1mc336858), 256);"}]},{"kind":"block","code":"background-color: --screenPx(var(--vidMode), var(--ci), round(down, var(--__1mc382062) / 256), var(--__1mc377126), var(--__1mc377421), 1, 8, 128, var(--vidPal));"}],"trailer":"}","folded":true},{"kind":"decl","code":".motherboard #p18357 {","children":[{"kind":"decl","code":"--ci:","children":[{"kind":"value","code":"round(down, var(--__1mc336858) / 256);"}]},{"kind":"block","code":"background-color: --screenPx(var(--vidMode), var(--ci), round(down, var(--__1mc382062) / 256), var(--__1mc377126), var(--__1mc377421), 1, 4, 32, var(--vidPal));"}],"trailer":"}","folded":true},{"kind":"decl","code":".motherboard #p18358 {","children":[{"kind":"decl","code":"--ci:","children":[{"kind":"value","code":"mod(var(--__1mc336859), 256);"}]},{"kind":"block","code":"background-color: --screenPx(var(--vidMode), var(--ci), round(down, var(--__1mc382062) / 256), var(--__1mc377126), var(--__1mc377421), 1, 2, 8, var(--vidPal));"}],"trailer":"}","folded":true},{"kind":"decl","code":".motherboard #p18359 {","children":[{"kind":"decl","code":"--ci:","children":[{"kind":"value","code":"round(down, var(--__1mc336859) / 256);"}]},{"kind":"block","code":"background-color: --screenPx(var(--vidMode), var(--ci), round(down, var(--__1mc382062) / 256), var(--__1mc377126), var(--__1mc377421), 1, 1, 2, var(--vidPal));"}],"trailer":"}","folded":true},{"kind":"decl","code":".motherboard #p18360 {","children":[{"kind":"decl","code":"--ci:","children":[{"kind":"value","code":"mod(var(--__1mc336860), 256);"}]},{"kind":"block","code":"background-color: --screenPx(var(--vidMode), var(--ci), mod(var(--__1mc382063), 256), var(--__1mc377127), var(--__1mc377422), 1, 128, 128, var(--vidPal));"}],"trailer":"}","folded":true},{"kind":"decl","code":".motherboard #p18361 {","children":[{"kind":"decl","code":"--ci:","children":[{"kind":"value","code":"round(down, var(--__1mc336860) / 256);"}]},{"kind":"block","code":"background-color: --screenPx(var(--vidMode), var(--ci), mod(var(--__1mc382063), 256), var(--__1mc377127), var(--__1mc377422), 1, 64, 32, var(--vidPal));"}],"trailer":"}","folded":true},{"kind":"decl","code":".motherboard #p18362 {","children":[{"kind":"decl","code":"--ci:","children":[{"kind":"value","code":"mod(var(--__1mc336861), 256);"}]},{"kind":"block","code":"background-color: --screenPx(var(--vidMode), var(--ci), mod(var(--__1mc382063), 256), var(--__1mc377127), var(--__1mc377422), 1, 32, 8, var(--vidPal));"}],"trailer":"}","folded":true},{"kind":"decl","code":".motherboard #p18363 {","children":[{"kind":"decl","code":"--ci:","children":[{"kind":"value","code":"round(down, var(--__1mc336861) / 256);"}]},{"kind":"block","code":"background-color: --screenPx(var(--vidMode), var(--ci), mod(var(--__1mc382063), 256), var(--__1mc377127), var(--__1mc377422), 1, 16, 2, var(--vidPal));"}],"trailer":"}","folded":true},{"kind":"decl","code":".motherboard #p18364 {","children":[{"kind":"decl","code":"--ci:","children":[{"kind":"value","code":"mod(var(--__1mc336862), 256);"}]},{"kind":"block","code":"background-color: --screenPx(var(--vidMode), var(--ci), round(down, var(--__1mc382063) / 256), var(--__1mc377127), var(--__1mc377423), 1, 8, 128, var(--vidPal));"}],"trailer":"}","folded":true},{"kind":"decl","code":".motherboard #p18365 {","children":[{"kind":"decl","code":"--ci:","children":[{"kind":"value","code":"round(down, var(--__1mc336862) / 256);"}]},{"kind":"block","code":"background-color: --screenPx(var(--vidMode), var(--ci), round(down, var(--__1mc382063) / 256), var(--__1mc377127), var(--__1mc377423), 1, 4, 32, var(--vidPal));"}],"trailer":"}","folded":true},{"kind":"decl","code":".motherboard #p18366 {","children":[{"kind":"decl","code":"--ci:","children":[{"kind":"value","code":"mod(var(--__1mc336863), 256);"}]},{"kind":"block","code":"background-color: --screenPx(var(--vidMode), var(--ci), round(down, var(--__1mc382063) / 256), var(--__1mc377127), var(--__1mc377423), 1, 2, 8, var(--vidPal));"}],"trailer":"}","folded":true},{"kind":"decl","code":".motherboard #p18367 {","children":[{"kind":"decl","code":"--ci:","children":[{"kind":"value","code":"round(down, var(--__1mc336863) / 256);"}]},{"kind":"block","code":"background-color: --screenPx(var(--vidMode), var(--ci), round(down, var(--__1mc382063) / 256), var(--__1mc377127), var(--__1mc377423), 1, 1, 2, var(--vidPal));"}],"trailer":"}","folded":true},{"kind":"decl","code":".motherboard #p18368 {","children":[{"kind":"decl","code":"--ci:","children":[{"kind":"value","code":"mod(var(--__1mc336864), 256);"}]},{"kind":"block","code":"background-color: --screenPx(var(--vidMode), var(--ci), mod(var(--__1mc382064), 256), var(--__1mc377128), var(--__1mc377424), 1, 128, 128, var(--vidPal));"}],"trailer":"}","folded":true},{"kind":"decl","code":".motherboard #p18369 {","children":[{"kind":"decl","code":"--ci:","children":[{"kind":"value","code":"round(down, var(--__1mc336864) / 256);"}]},{"kind":"block","code":"background-color: --screenPx(var(--vidMode), var(--ci), mod(var(--__1mc382064), 256), var(--__1mc377128), var(--__1mc377424), 1, 64, 32, var(--vidPal));"}],"trailer":"}","folded":true},{"kind":"decl","code":".motherboard #p18370 {","children":[{"kind":"decl","code":"--ci:","children":[{"kind":"value","code":"mod(var(--__1mc336865), 256);"}]},{"kind":"block","code":"background-color: --screenPx(var(--vidMode), var(--ci), mod(var(--__1mc382064), 256), var(--__1mc377128), var(--__1mc377424), 1, 32, 8, var(--vidPal));"}],"trailer":"}","folded":true},{"kind":"decl","code":".motherboard #p18371 {","children":[{"kind":"decl","code":"--ci:","children":[{"kind":"value","code":"round(down, var(--__1mc336865) / 256);"}]},{"kind":"block","code":"background-color: --screenPx(var(--vidMode), var(--ci), mod(var(--__1mc382064), 256), var(--__1mc377128), var(--__1mc377424), 1, 16, 2, var(--vidPal));"}],"trailer":"}","folded":true},{"kind":"decl","code":".motherboard #p18372 {","children":[{"kind":"decl","code":"--ci:","children":[{"kind":"value","code":"mod(var(--__1mc336866), 256);"}]},{"kind":"block","code":"background-color: --screenPx(var(--vidMode), var(--ci), round(down, var(--__1mc382064) / 256), var(--__1mc377128), var(--__1mc377425), 1, 8, 128, var(--vidPal));"}],"trailer":"}","folded":true},{"kind":"decl","code":".motherboard #p18373 {","children":[{"kind":"decl","code":"--ci:","children":[{"kind":"value","code":"round(down, var(--__1mc336866) / 256);"}]},{"kind":"block","code":"background-color: --screenPx(var(--vidMode), var(--ci), round(down, var(--__1mc382064) / 256), var(--__1mc377128), var(--__1mc377425), 1, 4, 32, var(--vidPal));"}],"trailer":"}","folded":true},{"kind":"decl","code":".motherboard #p18374 {","children":[{"kind":"decl","code":"--ci:","children":[{"kind":"value","code":"mod(var(--__1mc336867), 256);"}]},{"kind":"block","code":"background-color: --screenPx(var(--vidMode), var(--ci), round(down, var(--__1mc382064) / 256), var(--__1mc377128), var(--__1mc377425), 1, 2, 8, var(--vidPal));"}],"trailer":"}","folded":true},{"kind":"decl","code":".motherboard #p18375 {","children":[{"kind":"decl","code":"--ci:","children":[{"kind":"value","code":"round(down, var(--__1mc336867) / 256);"}]},{"kind":"block","code":"background-color: --screenPx(var(--vidMode), var(--ci), round(down, var(--__1mc382064) / 256), var(--__1mc377128), var(--__1mc377425), 1, 1, 2, var(--vidPal));"}],"trailer":"}","folded":true},{"kind":"decl","code":".motherboard #p18376 {","children":[{"kind":"decl","code":"--ci:","children":[{"kind":"value","code":"mod(var(--__1mc336868), 256);"}]},{"kind":"block","code":"background-color: --screenPx(var(--vidMode), var(--ci), mod(var(--__1mc382065), 256), var(--__1mc377129), var(--__1mc377426), 1, 128, 128, var(--vidPal));"}],"trailer":"}","folded":true},{"kind":"decl","code":".motherboard #p18377 {","children":[{"kind":"decl","code":"--ci:","children":[{"kind":"value","code":"round(down, var(--__1mc336868) / 256);"}]},{"kind":"block","code":"background-color: --screenPx(var(--vidMode), var(--ci), mod(var(--__1mc382065), 256), var(--__1mc377129), var(--__1mc377426), 1, 64, 32, var(--vidPal));"}],"trailer":"}","folded":true},{"kind":"decl","code":".motherboard #p18378 {","children":[{"kind":"decl","code":"--ci:","children":[{"kind":"value","code":"mod(var(--__1mc336869), 256);"}]},{"kind":"block","code":"background-color: --screenPx(var(--vidMode), var(--ci), mod(var(--__1mc382065), 256), var(--__1mc377129), var(--__1mc377426), 1, 32, 8, var(--vidPal));"}],"trailer":"}","folded":true},{"kind":"decl","code":".motherboard #p18379 {","children":[{"kind":"decl","code":"--ci:","children":[{"kind":"value","code":"round(down, var(--__1mc336869) / 256);"}]},{"kind":"block","code":"background-color: --screenPx(var(--vidMode), var(--ci), mod(var(--__1mc382065), 256), var(--__1mc377129), var(--__1mc377426), 1, 16, 2, var(--vidPal));"}],"trailer":"}","folded":true},{"kind":"decl","code":".motherboard #p18380 {","children":[{"kind":"decl","code":"--ci:","children":[{"kind":"value","code":"mod(var(--__1mc336870), 256);"}]},{"kind":"block","code":"background-color: --screenPx(var(--vidMode), var(--ci), round(down, var(--__1mc382065) / 256), var(--__1mc377129), var(--__1mc377427), 1, 8, 128, var(--vidPal));"}],"trailer":"}","folded":true},{"kind":"decl","code":".motherboard #p18381 {","children":[{"kind":"decl","code":"--ci:","children":[{"kind":"value","code":"round(down, var(--__1mc336870) / 256);"}]},{"kind":"block","code":"background-color: --screenPx(var(--vidMode), var(--ci), round(down, var(--__1mc382065) / 256), var(--__1mc377129), var(--__1mc377427), 1, 4, 32, var(--vidPal));"}],"trailer":"}","folded":true},{"kind":"decl","code":".motherboard #p18382 {","children":[{"kind":"decl","code":"--ci:","children":[{"kind":"value","code":"mod(var(--__1mc336871), 256);"}]},{"kind":"block","code":"background-color: --screenPx(var(--vidMode), var(--ci), round(down, var(--__1mc382065) / 256), var(--__1mc377129), var(--__1mc377427), 1, 2, 8, var(--vidPal));"}],"trailer":"}","folded":true},{"kind":"decl","code":".motherboard #p18383 {","children":[{"kind":"decl","code":"--ci:","children":[{"kind":"value","code":"round(down, var(--__1mc336871) / 256);"}]},{"kind":"block","code":"background-color: --screenPx(var(--vidMode), var(--ci), round(down, var(--__1mc382065) / 256), var(--__1mc377129), var(--__1mc377427), 1, 1, 2, var(--vidPal));"}],"trailer":"}","folded":true},{"kind":"decl","code":".motherboard #p18384 {","children":[{"kind":"decl","code":"--ci:","children":[{"kind":"value","code":"mod(var(--__1mc336872), 256);"}]},{"kind":"block","code":"background-color: --screenPx(var(--vidMode), var(--ci), mod(var(--__1mc382066), 256), var(--__1mc377130), var(--__1mc377428), 1, 128, 128, var(--vidPal));"}],"trailer":"}","folded":true},{"kind":"decl","code":".motherboard #p18385 {","children":[{"kind":"decl","code":"--ci:","children":[{"kind":"value","code":"round(down, var(--__1mc336872) / 256);"}]},{"kind":"block","code":"background-color: --screenPx(var(--vidMode), var(--ci), mod(var(--__1mc382066), 256), var(--__1mc377130), var(--__1mc377428), 1, 64, 32, var(--vidPal));"}],"trailer":"}","folded":true},{"kind":"decl","code":".motherboard #p18386 {","children":[{"kind":"decl","code":"--ci:","children":[{"kind":"value","code":"mod(var(--__1mc336873), 256);"}]},{"kind":"block","code":"background-color: --screenPx(var(--vidMode), var(--ci), mod(var(--__1mc382066), 256), var(--__1mc377130), var(--__1mc377428), 1, 32, 8, var(--vidPal));"}],"trailer":"}","folded":true},{"kind":"decl","code":".motherboard #p18387 {","children":[{"kind":"decl","code":"--ci:","children":[{"kind":"value","code":"round(down, var(--__1mc336873) / 256);"}]},{"kind":"block","code":"background-color: --screenPx(var(--vidMode), var(--ci), mod(var(--__1mc382066), 256), var(--__1mc377130), var(--__1mc377428), 1, 16, 2, var(--vidPal));"}],"trailer":"}","folded":true},{"kind":"decl","code":".motherboard #p18388 {","children":[{"kind":"decl","code":"--ci:","children":[{"kind":"value","code":"mod(var(--__1mc336874), 256);"}]},{"kind":"block","code":"background-color: --screenPx(var(--vidMode), var(--ci), round(down, var(--__1mc382066) / 256), var(--__1mc377130), var(--__1mc377429), 1, 8, 128, var(--vidPal));"}],"trailer":"}","folded":true},{"kind":"decl","code":".motherboard #p18389 {","children":[{"kind":"decl","code":"--ci:","children":[{"kind":"value","code":"round(down, var(--__1mc336874) / 256);"}]},{"kind":"block","code":"background-color: --screenPx(var(--vidMode), var(--ci), round(down, var(--__1mc382066) / 256), var(--__1mc377130), var(--__1mc377429), 1, 4, 32, var(--vidPal));"}],"trailer":"}","folded":true},{"kind":"decl","code":".motherboard #p18390 {","children":[{"kind":"decl","code":"--ci:","children":[{"kind":"value","code":"mod(var(--__1mc336875), 256);"}]},{"kind":"block","code":"background-color: --screenPx(var(--vidMode), var(--ci), round(down, var(--__1mc382066) / 256), var(--__1mc377130), var(--__1mc377429), 1, 2, 8, var(--vidPal));"}],"trailer":"}","folded":true},{"kind":"decl","code":".motherboard #p18391 {","children":[{"kind":"decl","code":"--ci:","children":[{"kind":"value","code":"round(down, var(--__1mc336875) / 256);"}]},{"kind":"block","code":"background-color: --screenPx(var(--vidMode), var(--ci), round(down, var(--__1mc382066) / 256), var(--__1mc377130), var(--__1mc377429), 1, 1, 2, var(--vidPal));"}],"trailer":"}","folded":true},{"kind":"decl","code":".motherboard #p18392 {","children":[{"kind":"decl","code":"--ci:","children":[{"kind":"value","code":"mod(var(--__1mc336876), 256);"}]},{"kind":"block","code":"background-color: --screenPx(var(--vidMode), var(--ci), mod(var(--__1mc382067), 256), var(--__1mc377131), var(--__1mc377430), 1, 128, 128, var(--vidPal));"}],"trailer":"}","folded":true},{"kind":"decl","code":".motherboard #p18393 {","children":[{"kind":"decl","code":"--ci:","children":[{"kind":"value","code":"round(down, var(--__1mc336876) / 256);"}]},{"kind":"block","code":"background-color: --screenPx(var(--vidMode), var(--ci), mod(var(--__1mc382067), 256), var(--__1mc377131), var(--__1mc377430), 1, 64, 32, var(--vidPal));"}],"trailer":"}","folded":true},{"kind":"decl","code":".motherboard #p18394 {","children":[{"kind":"decl","code":"--ci:","children":[{"kind":"value","code":"mod(var(--__1mc336877), 256);"}]},{"kind":"block","code":"background-color: --screenPx(var(--vidMode), var(--ci), mod(var(--__1mc382067), 256), var(--__1mc377131), var(--__1mc377430), 1, 32, 8, var(--vidPal));"}],"trailer":"}","folded":true},{"kind":"decl","code":".motherboard #p18395 {","children":[{"kind":"decl","code":"--ci:","children":[{"kind":"value","code":"round(down, var(--__1mc336877) / 256);"}]},{"kind":"block","code":"background-color: --screenPx(var(--vidMode), var(--ci), mod(var(--__1mc382067), 256), var(--__1mc377131), var(--__1mc377430), 1, 16, 2, var(--vidPal));"}],"trailer":"}","folded":true},{"kind":"decl","code":".motherboard #p18396 {","children":[{"kind":"decl","code":"--ci:","children":[{"kind":"value","code":"mod(var(--__1mc336878), 256);"}]},{"kind":"block","code":"background-color: --screenPx(var(--vidMode), var(--ci), round(down, var(--__1mc382067) / 256), var(--__1mc377131), var(--__1mc377431), 1, 8, 128, var(--vidPal));"}],"trailer":"}","folded":true},{"kind":"decl","code":".motherboard #p18397 {","children":[{"kind":"decl","code":"--ci:","children":[{"kind":"value","code":"round(down, var(--__1mc336878) / 256);"}]},{"kind":"block","code":"background-color: --screenPx(var(--vidMode), var(--ci), round(down, var(--__1mc382067) / 256), var(--__1mc377131), var(--__1mc377431), 1, 4, 32, var(--vidPal));"}],"trailer":"}","folded":true},{"kind":"decl","code":".motherboard #p18398 {","children":[{"kind":"decl","code":"--ci:","children":[{"kind":"value","code":"mod(var(--__1mc336879), 256);"}]},{"kind":"block","code":"background-color: --screenPx(var(--vidMode), var(--ci), round(down, var(--__1mc382067) / 256), var(--__1mc377131), var(--__1mc377431), 1, 2, 8, var(--vidPal));"}],"trailer":"}","folded":true},{"kind":"decl","code":".motherboard #p18399 {","children":[{"kind":"decl","code":"--ci:","children":[{"kind":"value","code":"round(down, var(--__1mc336879) / 256);"}]},{"kind":"block","code":"background-color: --screenPx(var(--vidMode), var(--ci), round(down, var(--__1mc382067) / 256), var(--__1mc377131), var(--__1mc377431), 1, 1, 2, var(--vidPal));"}],"trailer":"}","folded":true},{"kind":"decl","code":".motherboard #p18400 {","children":[{"kind":"decl","code":"--ci:","children":[{"kind":"value","code":"mod(var(--__1mc336880), 256);"}]},{"kind":"block","code":"background-color: --screenPx(var(--vidMode), var(--ci), mod(var(--__1mc382068), 256), var(--__1mc377132), var(--__1mc377432), 1, 128, 128, var(--vidPal));"}],"trailer":"}","folded":true},{"kind":"decl","code":".motherboard #p18401 {","children":[{"kind":"decl","code":"--ci:","children":[{"kind":"value","code":"round(down, var(--__1mc336880) / 256);"}]},{"kind":"block","code":"background-color: --screenPx(var(--vidMode), var(--ci), mod(var(--__1mc382068), 256), var(--__1mc377132), var(--__1mc377432), 1, 64, 32, var(--vidPal));"}],"trailer":"}","folded":true},{"kind":"decl","code":".motherboard #p18402 {","children":[{"kind":"decl","code":"--ci:","children":[{"kind":"value","code":"mod(var(--__1mc336881), 256);"}]},{"kind":"block","code":"background-color: --screenPx(var(--vidMode), var(--ci), mod(var(--__1mc382068), 256), var(--__1mc377132), var(--__1mc377432), 1, 32, 8, var(--vidPal));"}],"trailer":"}","folded":true},{"kind":"decl","code":".motherboard #p18403 {","children":[{"kind":"decl","code":"--ci:","children":[{"kind":"value","code":"round(down, var(--__1mc336881) / 256);"}]},{"kind":"block","code":"background-color: --screenPx(var(--vidMode), var(--ci), mod(var(--__1mc382068), 256), var(--__1mc377132), var(--__1mc377432), 1, 16, 2, var(--vidPal));"}],"trailer":"}","folded":true},{"kind":"decl","code":".motherboard #p18404 {","children":[{"kind":"decl","code":"--ci:","children":[{"kind":"value","code":"mod(var(--__1mc336882), 256);"}]},{"kind":"block","code":"background-color: --screenPx(var(--vidMode), var(--ci), round(down, var(--__1mc382068) / 256), var(--__1mc377132), var(--__1mc377433), 1, 8, 128, var(--vidPal));"}],"trailer":"}","folded":true},{"kind":"decl","code":".motherboard #p18405 {","children":[{"kind":"decl","code":"--ci:","children":[{"kind":"value","code":"round(down, var(--__1mc336882) / 256);"}]},{"kind":"block","code":"background-color: --screenPx(var(--vidMode), var(--ci), round(down, var(--__1mc382068) / 256), var(--__1mc377132), var(--__1mc377433), 1, 4, 32, var(--vidPal));"}],"trailer":"}","folded":true},{"kind":"decl","code":".motherboard #p18406 {","children":[{"kind":"decl","code":"--ci:","children":[{"kind":"value","code":"mod(var(--__1mc336883), 256);"}]},{"kind":"block","code":"background-color: --screenPx(var(--vidMode), var(--ci), round(down, var(--__1mc382068) / 256), var(--__1mc377132), var(--__1mc377433), 1, 2, 8, var(--vidPal));"}],"trailer":"}","folded":true},{"kind":"decl","code":".motherboard #p18407 {","children":[{"kind":"decl","code":"--ci:","children":[{"kind":"value","code":"round(down, var(--__1mc336883) / 256);"}]},{"kind":"block","code":"background-color: --screenPx(var(--vidMode), var(--ci), round(down, var(--__1mc382068) / 256), var(--__1mc377132), var(--__1mc377433), 1, 1, 2, var(--vidPal));"}],"trailer":"}","folded":true},{"kind":"decl","code":".motherboard #p18408 {","children":[{"kind":"decl","code":"--ci:","children":[{"kind":"value","code":"mod(var(--__1mc336884), 256);"}]},{"kind":"block","code":"background-color: --screenPx(var(--vidMode), var(--ci), mod(var(--__1mc382069), 256), var(--__1mc377133), var(--__1mc377434), 1, 128, 128, var(--vidPal));"}],"trailer":"}","folded":true},{"kind":"decl","code":".motherboard #p18409 {","children":[{"kind":"decl","code":"--ci:","children":[{"kind":"value","code":"round(down, var(--__1mc336884) / 256);"}]},{"kind":"block","code":"background-color: --screenPx(var(--vidMode), var(--ci), mod(var(--__1mc382069), 256), var(--__1mc377133), var(--__1mc377434), 1, 64, 32, var(--vidPal));"}],"trailer":"}","folded":true},{"kind":"decl","code":".motherboard #p18410 {","children":[{"kind":"decl","code":"--ci:","children":[{"kind":"value","code":"mod(var(--__1mc336885), 256);"}]},{"kind":"block","code":"background-color: --screenPx(var(--vidMode), var(--ci), mod(var(--__1mc382069), 256), var(--__1mc377133), var(--__1mc377434), 1, 32, 8, var(--vidPal));"}],"trailer":"}","folded":true},{"kind":"decl","code":".motherboard #p18411 {","children":[{"kind":"decl","code":"--ci:","children":[{"kind":"value","code":"round(down, var(--__1mc336885) / 256);"}]},{"kind":"block","code":"background-color: --screenPx(var(--vidMode), var(--ci), mod(var(--__1mc382069), 256), var(--__1mc377133), var(--__1mc377434), 1, 16, 2, var(--vidPal));"}],"trailer":"}","folded":true},{"kind":"decl","code":".motherboard #p18412 {","children":[{"kind":"decl","code":"--ci:","children":[{"kind":"value","code":"mod(var(--__1mc336886), 256);"}]},{"kind":"block","code":"background-color: --screenPx(var(--vidMode), var(--ci), round(down, var(--__1mc382069) / 256), var(--__1mc377133), var(--__1mc377435), 1, 8, 128, var(--vidPal));"}],"trailer":"}","folded":true},{"kind":"decl","code":".motherboard #p18413 {","children":[{"kind":"decl","code":"--ci:","children":[{"kind":"value","code":"round(down, var(--__1mc336886) / 256);"}]},{"kind":"block","code":"background-color: --screenPx(var(--vidMode), var(--ci), round(down, var(--__1mc382069) / 256), var(--__1mc377133), var(--__1mc377435), 1, 4, 32, var(--vidPal));"}],"trailer":"}","folded":true},{"kind":"decl","code":".motherboard #p18414 {","children":[{"kind":"decl","code":"--ci:","children":[{"kind":"value","code":"mod(var(--__1mc336887), 256);"}]},{"kind":"block","code":"background-color: --screenPx(var(--vidMode), var(--ci), round(down, var(--__1mc382069) / 256), var(--__1mc377133), var(--__1mc377435), 1, 2, 8, var(--vidPal));"}],"trailer":"}","folded":true},{"kind":"decl","code":".motherboard #p18415 {","children":[{"kind":"decl","code":"--ci:","children":[{"kind":"value","code":"round(down, var(--__1mc336887) / 256);"}]},{"kind":"block","code":"background-color: --screenPx(var(--vidMode), var(--ci), round(down, var(--__1mc382069) / 256), var(--__1mc377133), var(--__1mc377435), 1, 1, 2, var(--vidPal));"}],"trailer":"}","folded":true},{"kind":"decl","code":".motherboard #p18416 {","children":[{"kind":"decl","code":"--ci:","children":[{"kind":"value","code":"mod(var(--__1mc336888), 256);"}]},{"kind":"block","code":"background-color: --screenPx(var(--vidMode), var(--ci), mod(var(--__1mc382070), 256), var(--__1mc377134), var(--__1mc377436), 1, 128, 128, var(--vidPal));"}],"trailer":"}","folded":true},{"kind":"decl","code":".motherboard #p18417 {","children":[{"kind":"decl","code":"--ci:","children":[{"kind":"value","code":"round(down, var(--__1mc336888) / 256);"}]},{"kind":"block","code":"background-color: --screenPx(var(--vidMode), var(--ci), mod(var(--__1mc382070), 256), var(--__1mc377134), var(--__1mc377436), 1, 64, 32, var(--vidPal));"}],"trailer":"}","folded":true},{"kind":"decl","code":".motherboard #p18418 {","children":[{"kind":"decl","code":"--ci:","children":[{"kind":"value","code":"mod(var(--__1mc336889), 256);"}]},{"kind":"block","code":"background-color: --screenPx(var(--vidMode), var(--ci), mod(var(--__1mc382070), 256), var(--__1mc377134), var(--__1mc377436), 1, 32, 8, var(--vidPal));"}],"trailer":"}","folded":true},{"kind":"decl","code":".motherboard #p18419 {","children":[{"kind":"decl","code":"--ci:","children":[{"kind":"value","code":"round(down, var(--__1mc336889) / 256);"}]},{"kind":"block","code":"background-color: --screenPx(var(--vidMode), var(--ci), mod(var(--__1mc382070), 256), var(--__1mc377134), var(--__1mc377436), 1, 16, 2, var(--vidPal));"}],"trailer":"}","folded":true},{"kind":"decl","code":".motherboard #p18420 {","children":[{"kind":"decl","code":"--ci:","children":[{"kind":"value","code":"mod(var(--__1mc336890), 256);"}]},{"kind":"block","code":"background-color: --screenPx(var(--vidMode), var(--ci), round(down, var(--__1mc382070) / 256), var(--__1mc377134), var(--__1mc377437), 1, 8, 128, var(--vidPal));"}],"trailer":"}","folded":true},{"kind":"decl","code":".motherboard #p18421 {","children":[{"kind":"decl","code":"--ci:","children":[{"kind":"value","code":"round(down, var(--__1mc336890) / 256);"}]},{"kind":"block","code":"background-color: --screenPx(var(--vidMode), var(--ci), round(down, var(--__1mc382070) / 256), var(--__1mc377134), var(--__1mc377437), 1, 4, 32, var(--vidPal));"}],"trailer":"}","folded":true},{"kind":"decl","code":".motherboard #p18422 {","children":[{"kind":"decl","code":"--ci:","children":[{"kind":"value","code":"mod(var(--__1mc336891), 256);"}]},{"kind":"block","code":"background-color: --screenPx(var(--vidMode), var(--ci), round(down, var(--__1mc382070) / 256), var(--__1mc377134), var(--__1mc377437), 1, 2, 8, var(--vidPal));"}],"trailer":"}","folded":true}],"next":{"ref":"screen/147","remaining":45577}}