{"nodes":[{"kind":"decl","code":".motherboard #p39505 {","children":[{"kind":"decl","code":"--ci:","children":[{"kind":"value","code":"round(down, var(--__1mc347432) / 256);"}]},{"kind":"block","code":"background-color: --screenPx(var(--vidMode), var(--ci), mod(var(--__1mc383386), 256), var(--__1mc377450), var(--__1mc378068), 3, 64, 32, var(--vidPal));"}],"trailer":"}","folded":true},{"kind":"decl","code":".motherboard #p39506 {","children":[{"kind":"decl","code":"--ci:","children":[{"kind":"value","code":"mod(var(--__1mc347433), 256);"}]},{"kind":"block","code":"background-color: --screenPx(var(--vidMode), var(--ci), mod(var(--__1mc383386), 256), var(--__1mc377450), var(--__1mc378068), 3, 32, 8, var(--vidPal));"}],"trailer":"}","folded":true},{"kind":"decl","code":".motherboard #p39507 {","children":[{"kind":"decl","code":"--ci:","children":[{"kind":"value","code":"round(down, var(--__1mc347433) / 256);"}]},{"kind":"block","code":"background-color: --screenPx(var(--vidMode), var(--ci), mod(var(--__1mc383386), 256), var(--__1mc377450), var(--__1mc378068), 3, 16, 2, var(--vidPal));"}],"trailer":"}","folded":true},{"kind":"decl","code":".motherboard #p39508 {","children":[{"kind":"decl","code":"--ci:","children":[{"kind":"value","code":"mod(var(--__1mc347434), 256);"}]},{"kind":"block","code":"background-color: --screenPx(var(--vidMode), var(--ci), round(down, var(--__1mc383386) / 256), var(--__1mc377450), var(--__1mc378069), 3, 8, 128, var(--vidPal));"}],"trailer":"}","folded":true},{"kind":"decl","code":".motherboard #p39509 {","children":[{"kind":"decl","code":"--ci:","children":[{"kind":"value","code":"round(down, var(--__1mc347434) / 256);"}]},{"kind":"block","code":"background-color: --screenPx(var(--vidMode), var(--ci), round(down, var(--__1mc383386) / 256), var(--__1mc377450), var(--__1mc378069), 3, 4, 32, var(--vidPal));"}],"trailer":"}","folded":true},{"kind":"decl","code":".motherboard #p39510 {","children":[{"kind":"decl","code":"--ci:","children":[{"kind":"value","code":"mod(var(--__1mc347435), 256);"}]},{"kind":"block","code":"background-color: --screenPx(var(--vidMode), var(--ci), round(down, var(--__1mc383386) / 256), var(--__1mc377450), var(--__1mc378069), 3, 2, 8, var(--vidPal));"}],"trailer":"}","folded":true},{"kind":"decl","code":".motherboard #p39511 {","children":[{"kind":"decl","code":"--ci:","children":[{"kind":"value","code":"round(down, var(--__1mc347435) / 256);"}]},{"kind":"block","code":"background-color: --screenPx(var(--vidMode), var(--ci), round(down, var(--__1mc383386) / 256), var(--__1mc377450), var(--__1mc378069), 3, 1, 2, var(--vidPal));"}],"trailer":"}","folded":true},{"kind":"decl","code":".motherboard #p39512 {","children":[{"kind":"decl","code":"--ci:","children":[{"kind":"value","code":"mod(var(--__1mc347436), 256);"}]},{"kind":"block","code":"background-color: --screenPx(var(--vidMode), var(--ci), mod(var(--__1mc383387), 256), var(--__1mc377451), var(--__1mc378070), 3, 128, 128, var(--vidPal));"}],"trailer":"}","folded":true},{"kind":"decl","code":".motherboard #p39513 {","children":[{"kind":"decl","code":"--ci:","children":[{"kind":"value","code":"round(down, var(--__1mc347436) / 256);"}]},{"kind":"block","code":"background-color: --screenPx(var(--vidMode), var(--ci), mod(var(--__1mc383387), 256), var(--__1mc377451), var(--__1mc378070), 3, 64, 32, var(--vidPal));"}],"trailer":"}","folded":true},{"kind":"decl","code":".motherboard #p39514 {","children":[{"kind":"decl","code":"--ci:","children":[{"kind":"value","code":"mod(var(--__1mc347437), 256);"}]},{"kind":"block","code":"background-color: --screenPx(var(--vidMode), var(--ci), mod(var(--__1mc383387), 256), var(--__1mc377451), var(--__1mc378070), 3, 32, 8, var(--vidPal));"}],"trailer":"}","folded":true},{"kind":"decl","code":".motherboard #p39515 {","children":[{"kind":"decl","code":"--ci:","children":[{"kind":"value","code":"round(down, var(--__1mc347437) / 256);"}]},{"kind":"block","code":"background-color: --screenPx(var(--vidMode), var(--ci), mod(var(--__1mc383387), 256), var(--__1mc377451), var(--__1mc378070), 3, 16, 2, var(--vidPal));"}],"trailer":"}","folded":true},{"kind":"decl","code":".motherboard #p39516 {","children":[{"kind":"decl","code":"--ci:","children":[{"kind":"value","code":"mod(var(--__1mc347438), 256);"}]},{"kind":"block","code":"background-color: --screenPx(var(--vidMode), var(--ci), round(down, var(--__1mc383387) / 256), var(--__1mc377451), var(--__1mc378071), 3, 8, 128, var(--vidPal));"}],"trailer":"}","folded":true},{"kind":"decl","code":".motherboard #p39517 {","children":[{"kind":"decl","code":"--ci:","children":[{"kind":"value","code":"round(down, var(--__1mc347438) / 256);"}]},{"kind":"block","code":"background-color: --screenPx(var(--vidMode), var(--ci), round(down, var(--__1mc383387) / 256), var(--__1mc377451), var(--__1mc378071), 3, 4, 32, var(--vidPal));"}],"trailer":"}","folded":true},{"kind":"decl","code":".motherboard #p39518 {","children":[{"kind":"decl","code":"--ci:","children":[{"kind":"value","code":"mod(var(--__1mc347439), 256);"}]},{"kind":"block","code":"background-color: --screenPx(var(--vidMode), var(--ci), round(down, var(--__1mc383387) / 256), var(--__1mc377451), var(--__1mc378071), 3, 2, 8, var(--vidPal));"}],"trailer":"}","folded":true},{"kind":"decl","code":".motherboard #p39519 {","children":[{"kind":"decl","code":"--ci:","children":[{"kind":"value","code":"round(down, var(--__1mc347439) / 256);"}]},{"kind":"block","code":"background-color: --screenPx(var(--vidMode), var(--ci), round(down, var(--__1mc383387) / 256), var(--__1mc377451), var(--__1mc378071), 3, 1, 2, var(--vidPal));"}],"trailer":"}","folded":true},{"kind":"decl","code":".motherboard #p39520 {","children":[{"kind":"decl","code":"--ci:","children":[{"kind":"value","code":"mod(var(--__1mc347440), 256);"}]},{"kind":"block","code":"background-color: --screenPx(var(--vidMode), var(--ci), mod(var(--__1mc383388), 256), var(--__1mc377452), var(--__1mc378072), 3, 128, 128, var(--vidPal));"}],"trailer":"}","folded":true},{"kind":"decl","code":".motherboard #p39521 {","children":[{"kind":"decl","code":"--ci:","children":[{"kind":"value","code":"round(down, var(--__1mc347440) / 256);"}]},{"kind":"block","code":"background-color: --screenPx(var(--vidMode), var(--ci), mod(var(--__1mc383388), 256), var(--__1mc377452), var(--__1mc378072), 3, 64, 32, var(--vidPal));"}],"trailer":"}","folded":true},{"kind":"decl","code":".motherboard #p39522 {","children":[{"kind":"decl","code":"--ci:","children":[{"kind":"value","code":"mod(var(--__1mc347441), 256);"}]},{"kind":"block","code":"background-color: --screenPx(var(--vidMode), var(--ci), mod(var(--__1mc383388), 256), var(--__1mc377452), var(--__1mc378072), 3, 32, 8, var(--vidPal));"}],"trailer":"}","folded":true},{"kind":"decl","code":".motherboard #p39523 {","children":[{"kind":"decl","code":"--ci:","children":[{"kind":"value","code":"round(down, var(--__1mc347441) / 256);"}]},{"kind":"block","code":"background-color: --screenPx(var(--vidMode), var(--ci), mod(var(--__1mc383388), 256), var(--__1mc377452), var(--__1mc378072), 3, 16, 2, var(--vidPal));"}],"trailer":"}","folded":true},{"kind":"decl","code":".motherboard #p39524 {","children":[{"kind":"decl","code":"--ci:","children":[{"kind":"value","code":"mod(var(--__1mc347442), 256);"}]},{"kind":"block","code":"background-color: --screenPx(var(--vidMode), var(--ci), round(down, var(--__1mc383388) / 256), var(--__1mc377452), var(--__1mc378073), 3, 8, 128, var(--vidPal));"}],"trailer":"}","folded":true},{"kind":"decl","code":".motherboard #p39525 {","children":[{"kind":"decl","code":"--ci:","children":[{"kind":"value","code":"round(down, var(--__1mc347442) / 256);"}]},{"kind":"block","code":"background-color: --screenPx(var(--vidMode), var(--ci), round(down, var(--__1mc383388) / 256), var(--__1mc377452), var(--__1mc378073), 3, 4, 32, var(--vidPal));"}],"trailer":"}","folded":true},{"kind":"decl","code":".motherboard #p39526 {","children":[{"kind":"decl","code":"--ci:","children":[{"kind":"value","code":"mod(var(--__1mc347443), 256);"}]},{"kind":"block","code":"background-color: --screenPx(var(--vidMode), var(--ci), round(down, var(--__1mc383388) / 256), var(--__1mc377452), var(--__1mc378073), 3, 2, 8, var(--vidPal));"}],"trailer":"}","folded":true},{"kind":"decl","code":".motherboard #p39527 {","children":[{"kind":"decl","code":"--ci:","children":[{"kind":"value","code":"round(down, var(--__1mc347443) / 256);"}]},{"kind":"block","code":"background-color: --screenPx(var(--vidMode), var(--ci), round(down, var(--__1mc383388) / 256), var(--__1mc377452), var(--__1mc378073), 3, 1, 2, var(--vidPal));"}],"trailer":"}","folded":true},{"kind":"decl","code":".motherboard #p39528 {","children":[{"kind":"decl","code":"--ci:","children":[{"kind":"value","code":"mod(var(--__1mc347444), 256);"}]},{"kind":"block","code":"background-color: --screenPx(var(--vidMode), var(--ci), mod(var(--__1mc383389), 256), var(--__1mc377453), var(--__1mc378074), 3, 128, 128, var(--vidPal));"}],"trailer":"}","folded":true},{"kind":"decl","code":".motherboard #p39529 {","children":[{"kind":"decl","code":"--ci:","children":[{"kind":"value","code":"round(down, var(--__1mc347444) / 256);"}]},{"kind":"block","code":"background-color: --screenPx(var(--vidMode), var(--ci), mod(var(--__1mc383389), 256), var(--__1mc377453), var(--__1mc378074), 3, 64, 32, var(--vidPal));"}],"trailer":"}","folded":true},{"kind":"decl","code":".motherboard #p39530 {","children":[{"kind":"decl","code":"--ci:","children":[{"kind":"value","code":"mod(var(--__1mc347445), 256);"}]},{"kind":"block","code":"background-color: --screenPx(var(--vidMode), var(--ci), mod(var(--__1mc383389), 256), var(--__1mc377453), var(--__1mc378074), 3, 32, 8, var(--vidPal));"}],"trailer":"}","folded":true},{"kind":"decl","code":".motherboard #p39531 {","children":[{"kind":"decl","code":"--ci:","children":[{"kind":"value","code":"round(down, var(--__1mc347445) / 256);"}]},{"kind":"block","code":"background-color: --screenPx(var(--vidMode), var(--ci), mod(var(--__1mc383389), 256), var(--__1mc377453), var(--__1mc378074), 3, 16, 2, var(--vidPal));"}],"trailer":"}","folded":true},{"kind":"decl","code":".motherboard #p39532 {","children":[{"kind":"decl","code":"--ci:","children":[{"kind":"value","code":"mod(var(--__1mc347446), 256);"}]},{"kind":"block","code":"background-color: --screenPx(var(--vidMode), var(--ci), round(down, var(--__1mc383389) / 256), var(--__1mc377453), var(--__1mc378075), 3, 8, 128, var(--vidPal));"}],"trailer":"}","folded":true},{"kind":"decl","code":".motherboard #p39533 {","children":[{"kind":"decl","code":"--ci:","children":[{"kind":"value","code":"round(down, var(--__1mc347446) / 256);"}]},{"kind":"block","code":"background-color: --screenPx(var(--vidMode), var(--ci), round(down, var(--__1mc383389) / 256), var(--__1mc377453), var(--__1mc378075), 3, 4, 32, var(--vidPal));"}],"trailer":"}","folded":true},{"kind":"decl","code":".motherboard #p39534 {","children":[{"kind":"decl","code":"--ci:","children":[{"kind":"value","code":"mod(var(--__1mc347447), 256);"}]},{"kind":"block","code":"background-color: --screenPx(var(--vidMode), var(--ci), round(down, var(--__1mc383389) / 256), var(--__1mc377453), var(--__1mc378075), 3, 2, 8, var(--vidPal));"}],"trailer":"}","folded":true},{"kind":"decl","code":".motherboard #p39535 {","children":[{"kind":"decl","code":"--ci:","children":[{"kind":"value","code":"round(down, var(--__1mc347447) / 256);"}]},{"kind":"block","code":"background-color: --screenPx(var(--vidMode), var(--ci), round(down, var(--__1mc383389) / 256), var(--__1mc377453), var(--__1mc378075), 3, 1, 2, var(--vidPal));"}],"trailer":"}","folded":true},{"kind":"decl","code":".motherboard #p39536 {","children":[{"kind":"decl","code":"--ci:","children":[{"kind":"value","code":"mod(var(--__1mc347448), 256);"}]},{"kind":"block","code":"background-color: --screenPx(var(--vidMode), var(--ci), mod(var(--__1mc383390), 256), var(--__1mc377454), var(--__1mc378076), 3, 128, 128, var(--vidPal));"}],"trailer":"}","folded":true},{"kind":"decl","code":".motherboard #p39537 {","children":[{"kind":"decl","code":"--ci:","children":[{"kind":"value","code":"round(down, var(--__1mc347448) / 256);"}]},{"kind":"block","code":"background-color: --screenPx(var(--vidMode), var(--ci), mod(var(--__1mc383390), 256), var(--__1mc377454), var(--__1mc378076), 3, 64, 32, var(--vidPal));"}],"trailer":"}","folded":true},{"kind":"decl","code":".motherboard #p39538 {","children":[{"kind":"decl","code":"--ci:","children":[{"kind":"value","code":"mod(var(--__1mc347449), 256);"}]},{"kind":"block","code":"background-color: --screenPx(var(--vidMode), var(--ci), mod(var(--__1mc383390), 256), var(--__1mc377454), var(--__1mc378076), 3, 32, 8, var(--vidPal));"}],"trailer":"}","folded":true},{"kind":"decl","code":".motherboard #p39539 {","children":[{"kind":"decl","code":"--ci:","children":[{"kind":"value","code":"round(down, var(--__1mc347449) / 256);"}]},{"kind":"block","code":"background-color: --screenPx(var(--vidMode), var(--ci), mod(var(--__1mc383390), 256), var(--__1mc377454), var(--__1mc378076), 3, 16, 2, var(--vidPal));"}],"trailer":"}","folded":true},{"kind":"decl","code":".motherboard #p39540 {","children":[{"kind":"decl","code":"--ci:","children":[{"kind":"value","code":"mod(var(--__1mc347450), 256);"}]},{"kind":"block","code":"background-color: --screenPx(var(--vidMode), var(--ci), round(down, var(--__1mc383390) / 256), var(--__1mc377454), var(--__1mc378077), 3, 8, 128, var(--vidPal));"}],"trailer":"}","folded":true},{"kind":"decl","code":".motherboard #p39541 {","children":[{"kind":"decl","code":"--ci:","children":[{"kind":"value","code":"round(down, var(--__1mc347450) / 256);"}]},{"kind":"block","code":"background-color: --screenPx(var(--vidMode), var(--ci), round(down, var(--__1mc383390) / 256), var(--__1mc377454), var(--__1mc378077), 3, 4, 32, var(--vidPal));"}],"trailer":"}","folded":true},{"kind":"decl","code":".motherboard #p39542 {","children":[{"kind":"decl","code":"--ci:","children":[{"kind":"value","code":"mod(var(--__1mc347451), 256);"}]},{"kind":"block","code":"background-color: --screenPx(var(--vidMode), var(--ci), round(down, var(--__1mc383390) / 256), var(--__1mc377454), var(--__1mc378077), 3, 2, 8, var(--vidPal));"}],"trailer":"}","folded":true},{"kind":"decl","code":".motherboard #p39543 {","children":[{"kind":"decl","code":"--ci:","children":[{"kind":"value","code":"round(down, var(--__1mc347451) / 256);"}]},{"kind":"block","code":"background-color: --screenPx(var(--vidMode), var(--ci), round(down, var(--__1mc383390) / 256), var(--__1mc377454), var(--__1mc378077), 3, 1, 2, var(--vidPal));"}],"trailer":"}","folded":true},{"kind":"decl","code":".motherboard #p39544 {","children":[{"kind":"decl","code":"--ci:","children":[{"kind":"value","code":"mod(var(--__1mc347452), 256);"}]},{"kind":"block","code":"background-color: --screenPx(var(--vidMode), var(--ci), mod(var(--__1mc383391), 256), var(--__1mc377455), var(--__1mc378078), 3, 128, 128, var(--vidPal));"}],"trailer":"}","folded":true},{"kind":"decl","code":".motherboard #p39545 {","children":[{"kind":"decl","code":"--ci:","children":[{"kind":"value","code":"round(down, var(--__1mc347452) / 256);"}]},{"kind":"block","code":"background-color: --screenPx(var(--vidMode), var(--ci), mod(var(--__1mc383391), 256), var(--__1mc377455), var(--__1mc378078), 3, 64, 32, var(--vidPal));"}],"trailer":"}","folded":true},{"kind":"decl","code":".motherboard #p39546 {","children":[{"kind":"decl","code":"--ci:","children":[{"kind":"value","code":"mod(var(--__1mc347453), 256);"}]},{"kind":"block","code":"background-color: --screenPx(var(--vidMode), var(--ci), mod(var(--__1mc383391), 256), var(--__1mc377455), var(--__1mc378078), 3, 32, 8, var(--vidPal));"}],"trailer":"}","folded":true},{"kind":"decl","code":".motherboard #p39547 {","children":[{"kind":"decl","code":"--ci:","children":[{"kind":"value","code":"round(down, var(--__1mc347453) / 256);"}]},{"kind":"block","code":"background-color: --screenPx(var(--vidMode), var(--ci), mod(var(--__1mc383391), 256), var(--__1mc377455), var(--__1mc378078), 3, 16, 2, var(--vidPal));"}],"trailer":"}","folded":true},{"kind":"decl","code":".motherboard #p39548 {","children":[{"kind":"decl","code":"--ci:","children":[{"kind":"value","code":"mod(var(--__1mc347454), 256);"}]},{"kind":"block","code":"background-color: --screenPx(var(--vidMode), var(--ci), round(down, var(--__1mc383391) / 256), var(--__1mc377455), var(--__1mc378079), 3, 8, 128, var(--vidPal));"}],"trailer":"}","folded":true},{"kind":"decl","code":".motherboard #p39549 {","children":[{"kind":"decl","code":"--ci:","children":[{"kind":"value","code":"round(down, var(--__1mc347454) / 256);"}]},{"kind":"block","code":"background-color: --screenPx(var(--vidMode), var(--ci), round(down, var(--__1mc383391) / 256), var(--__1mc377455), var(--__1mc378079), 3, 4, 32, var(--vidPal));"}],"trailer":"}","folded":true},{"kind":"decl","code":".motherboard #p39550 {","children":[{"kind":"decl","code":"--ci:","children":[{"kind":"value","code":"mod(var(--__1mc347455), 256);"}]},{"kind":"block","code":"background-color: --screenPx(var(--vidMode), var(--ci), round(down, var(--__1mc383391) / 256), var(--__1mc377455), var(--__1mc378079), 3, 2, 8, var(--vidPal));"}],"trailer":"}","folded":true},{"kind":"decl","code":".motherboard #p39551 {","children":[{"kind":"decl","code":"--ci:","children":[{"kind":"value","code":"round(down, var(--__1mc347455) / 256);"}]},{"kind":"block","code":"background-color: --screenPx(var(--vidMode), var(--ci), round(down, var(--__1mc383391) / 256), var(--__1mc377455), var(--__1mc378079), 3, 1, 2, var(--vidPal));"}],"trailer":"}","folded":true},{"kind":"decl","code":".motherboard #p39552 {","children":[{"kind":"decl","code":"--ci:","children":[{"kind":"value","code":"mod(var(--__1mc347456), 256);"}]},{"kind":"block","code":"background-color: --screenPx(var(--vidMode), var(--ci), mod(var(--__1mc383392), 256), var(--__1mc377456), var(--__1mc378080), 3, 128, 128, var(--vidPal));"}],"trailer":"}","folded":true},{"kind":"decl","code":".motherboard #p39553 {","children":[{"kind":"decl","code":"--ci:","children":[{"kind":"value","code":"round(down, var(--__1mc347456) / 256);"}]},{"kind":"block","code":"background-color: --screenPx(var(--vidMode), var(--ci), mod(var(--__1mc383392), 256), var(--__1mc377456), var(--__1mc378080), 3, 64, 32, var(--vidPal));"}],"trailer":"}","folded":true},{"kind":"decl","code":".motherboard #p39554 {","children":[{"kind":"decl","code":"--ci:","children":[{"kind":"value","code":"mod(var(--__1mc347457), 256);"}]},{"kind":"block","code":"background-color: --screenPx(var(--vidMode), var(--ci), mod(var(--__1mc383392), 256), var(--__1mc377456), var(--__1mc378080), 3, 32, 8, var(--vidPal));"}],"trailer":"}","folded":true},{"kind":"decl","code":".motherboard #p39555 {","children":[{"kind":"decl","code":"--ci:","children":[{"kind":"value","code":"round(down, var(--__1mc347457) / 256);"}]},{"kind":"block","code":"background-color: --screenPx(var(--vidMode), var(--ci), mod(var(--__1mc383392), 256), var(--__1mc377456), var(--__1mc378080), 3, 16, 2, var(--vidPal));"}],"trailer":"}","folded":true},{"kind":"decl","code":".motherboard #p39556 {","children":[{"kind":"decl","code":"--ci:","children":[{"kind":"value","code":"mod(var(--__1mc347458), 256);"}]},{"kind":"block","code":"background-color: --screenPx(var(--vidMode), var(--ci), round(down, var(--__1mc383392) / 256), var(--__1mc377456), var(--__1mc378081), 3, 8, 128, var(--vidPal));"}],"trailer":"}","folded":true},{"kind":"decl","code":".motherboard #p39557 {","children":[{"kind":"decl","code":"--ci:","children":[{"kind":"value","code":"round(down, var(--__1mc347458) / 256);"}]},{"kind":"block","code":"background-color: --screenPx(var(--vidMode), var(--ci), round(down, var(--__1mc383392) / 256), var(--__1mc377456), var(--__1mc378081), 3, 4, 32, var(--vidPal));"}],"trailer":"}","folded":true},{"kind":"decl","code":".motherboard #p39558 {","children":[{"kind":"decl","code":"--ci:","children":[{"kind":"value","code":"mod(var(--__1mc347459), 256);"}]},{"kind":"block","code":"background-color: --screenPx(var(--vidMode), var(--ci), round(down, var(--__1mc383392) / 256), var(--__1mc377456), var(--__1mc378081), 3, 2, 8, var(--vidPal));"}],"trailer":"}","folded":true},{"kind":"decl","code":".motherboard #p39559 {","children":[{"kind":"decl","code":"--ci:","children":[{"kind":"value","code":"round(down, var(--__1mc347459) / 256);"}]},{"kind":"block","code":"background-color: --screenPx(var(--vidMode), var(--ci), round(down, var(--__1mc383392) / 256), var(--__1mc377456), var(--__1mc378081), 3, 1, 2, var(--vidPal));"}],"trailer":"}","folded":true},{"kind":"decl","code":".motherboard #p39560 {","children":[{"kind":"decl","code":"--ci:","children":[{"kind":"value","code":"mod(var(--__1mc347460), 256);"}]},{"kind":"block","code":"background-color: --screenPx(var(--vidMode), var(--ci), mod(var(--__1mc383393), 256), var(--__1mc377457), var(--__1mc378082), 3, 128, 128, var(--vidPal));"}],"trailer":"}","folded":true},{"kind":"decl","code":".motherboard #p39561 {","children":[{"kind":"decl","code":"--ci:","children":[{"kind":"value","code":"round(down, var(--__1mc347460) / 256);"}]},{"kind":"block","code":"background-color: --screenPx(var(--vidMode), var(--ci), mod(var(--__1mc383393), 256), var(--__1mc377457), var(--__1mc378082), 3, 64, 32, var(--vidPal));"}],"trailer":"}","folded":true},{"kind":"decl","code":".motherboard #p39562 {","children":[{"kind":"decl","code":"--ci:","children":[{"kind":"value","code":"mod(var(--__1mc347461), 256);"}]},{"kind":"block","code":"background-color: --screenPx(var(--vidMode), var(--ci), mod(var(--__1mc383393), 256), var(--__1mc377457), var(--__1mc378082), 3, 32, 8, var(--vidPal));"}],"trailer":"}","folded":true},{"kind":"decl","code":".motherboard #p39563 {","children":[{"kind":"decl","code":"--ci:","children":[{"kind":"value","code":"round(down, var(--__1mc347461) / 256);"}]},{"kind":"block","code":"background-color: --screenPx(var(--vidMode), var(--ci), mod(var(--__1mc383393), 256), var(--__1mc377457), var(--__1mc378082), 3, 16, 2, var(--vidPal));"}],"trailer":"}","folded":true},{"kind":"decl","code":".motherboard #p39564 {","children":[{"kind":"decl","code":"--ci:","children":[{"kind":"value","code":"mod(var(--__1mc347462), 256);"}]},{"kind":"block","code":"background-color: --screenPx(var(--vidMode), var(--ci), round(down, var(--__1mc383393) / 256), var(--__1mc377457), var(--__1mc378083), 3, 8, 128, var(--vidPal));"}],"trailer":"}","folded":true},{"kind":"decl","code":".motherboard #p39565 {","children":[{"kind":"decl","code":"--ci:","children":[{"kind":"value","code":"round(down, var(--__1mc347462) / 256);"}]},{"kind":"block","code":"background-color: --screenPx(var(--vidMode), var(--ci), round(down, var(--__1mc383393) / 256), var(--__1mc377457), var(--__1mc378083), 3, 4, 32, var(--vidPal));"}],"trailer":"}","folded":true},{"kind":"decl","code":".motherboard #p39566 {","children":[{"kind":"decl","code":"--ci:","children":[{"kind":"value","code":"mod(var(--__1mc347463), 256);"}]},{"kind":"block","code":"background-color: --screenPx(var(--vidMode), var(--ci), round(down, var(--__1mc383393) / 256), var(--__1mc377457), var(--__1mc378083), 3, 2, 8, var(--vidPal));"}],"trailer":"}","folded":true},{"kind":"decl","code":".motherboard #p39567 {","children":[{"kind":"decl","code":"--ci:","children":[{"kind":"value","code":"round(down, var(--__1mc347463) / 256);"}]},{"kind":"block","code":"background-color: --screenPx(var(--vidMode), var(--ci), round(down, var(--__1mc383393) / 256), var(--__1mc377457), var(--__1mc378083), 3, 1, 2, var(--vidPal));"}],"trailer":"}","folded":true},{"kind":"decl","code":".motherboard #p39568 {","children":[{"kind":"decl","code":"--ci:","children":[{"kind":"value","code":"mod(var(--__1mc347464), 256);"}]},{"kind":"block","code":"background-color: --screenPx(var(--vidMode), var(--ci), mod(var(--__1mc383394), 256), var(--__1mc377458), var(--__1mc378084), 3, 128, 128, var(--vidPal));"}],"trailer":"}","folded":true},{"kind":"decl","code":".motherboard #p39569 {","children":[{"kind":"decl","code":"--ci:","children":[{"kind":"value","code":"round(down, var(--__1mc347464) / 256);"}]},{"kind":"block","code":"background-color: --screenPx(var(--vidMode), var(--ci), mod(var(--__1mc383394), 256), var(--__1mc377458), var(--__1mc378084), 3, 64, 32, var(--vidPal));"}],"trailer":"}","folded":true},{"kind":"decl","code":".motherboard #p39570 {","children":[{"kind":"decl","code":"--ci:","children":[{"kind":"value","code":"mod(var(--__1mc347465), 256);"}]},{"kind":"block","code":"background-color: --screenPx(var(--vidMode), var(--ci), mod(var(--__1mc383394), 256), var(--__1mc377458), var(--__1mc378084), 3, 32, 8, var(--vidPal));"}],"trailer":"}","folded":true},{"kind":"decl","code":".motherboard #p39571 {","children":[{"kind":"decl","code":"--ci:","children":[{"kind":"value","code":"round(down, var(--__1mc347465) / 256);"}]},{"kind":"block","code":"background-color: --screenPx(var(--vidMode), var(--ci), mod(var(--__1mc383394), 256), var(--__1mc377458), var(--__1mc378084), 3, 16, 2, var(--vidPal));"}],"trailer":"}","folded":true},{"kind":"decl","code":".motherboard #p39572 {","children":[{"kind":"decl","code":"--ci:","children":[{"kind":"value","code":"mod(var(--__1mc347466), 256);"}]},{"kind":"block","code":"background-color: --screenPx(var(--vidMode), var(--ci), round(down, var(--__1mc383394) / 256), var(--__1mc377458), var(--__1mc378085), 3, 8, 128, var(--vidPal));"}],"trailer":"}","folded":true},{"kind":"decl","code":".motherboard #p39573 {","children":[{"kind":"decl","code":"--ci:","children":[{"kind":"value","code":"round(down, var(--__1mc347466) / 256);"}]},{"kind":"block","code":"background-color: --screenPx(var(--vidMode), var(--ci), round(down, var(--__1mc383394) / 256), var(--__1mc377458), var(--__1mc378085), 3, 4, 32, var(--vidPal));"}],"trailer":"}","folded":true},{"kind":"decl","code":".motherboard #p39574 {","children":[{"kind":"decl","code":"--ci:","children":[{"kind":"value","code":"mod(var(--__1mc347467), 256);"}]},{"kind":"block","code":"background-color: --screenPx(var(--vidMode), var(--ci), round(down, var(--__1mc383394) / 256), var(--__1mc377458), var(--__1mc378085), 3, 2, 8, var(--vidPal));"}],"trailer":"}","folded":true},{"kind":"decl","code":".motherboard #p39575 {","children":[{"kind":"decl","code":"--ci:","children":[{"kind":"value","code":"round(down, var(--__1mc347467) / 256);"}]},{"kind":"block","code":"background-color: --screenPx(var(--vidMode), var(--ci), round(down, var(--__1mc383394) / 256), var(--__1mc377458), var(--__1mc378085), 3, 1, 2, var(--vidPal));"}],"trailer":"}","folded":true},{"kind":"decl","code":".motherboard #p39576 {","children":[{"kind":"decl","code":"--ci:","children":[{"kind":"value","code":"mod(var(--__1mc347468), 256);"}]},{"kind":"block","code":"background-color: --screenPx(var(--vidMode), var(--ci), mod(var(--__1mc383395), 256), var(--__1mc377459), var(--__1mc378086), 3, 128, 128, var(--vidPal));"}],"trailer":"}","folded":true},{"kind":"decl","code":".motherboard #p39577 {","children":[{"kind":"decl","code":"--ci:","children":[{"kind":"value","code":"round(down, var(--__1mc347468) / 256);"}]},{"kind":"block","code":"background-color: --screenPx(var(--vidMode), var(--ci), mod(var(--__1mc383395), 256), var(--__1mc377459), var(--__1mc378086), 3, 64, 32, var(--vidPal));"}],"trailer":"}","folded":true},{"kind":"decl","code":".motherboard #p39578 {","children":[{"kind":"decl","code":"--ci:","children":[{"kind":"value","code":"mod(var(--__1mc347469), 256);"}]},{"kind":"block","code":"background-color: --screenPx(var(--vidMode), var(--ci), mod(var(--__1mc383395), 256), var(--__1mc377459), var(--__1mc378086), 3, 32, 8, var(--vidPal));"}],"trailer":"}","folded":true},{"kind":"decl","code":".motherboard #p39579 {","children":[{"kind":"decl","code":"--ci:","children":[{"kind":"value","code":"round(down, var(--__1mc347469) / 256);"}]},{"kind":"block","code":"background-color: --screenPx(var(--vidMode), var(--ci), mod(var(--__1mc383395), 256), var(--__1mc377459), var(--__1mc378086), 3, 16, 2, var(--vidPal));"}],"trailer":"}","folded":true},{"kind":"decl","code":".motherboard #p39580 {","children":[{"kind":"decl","code":"--ci:","children":[{"kind":"value","code":"mod(var(--__1mc347470), 256);"}]},{"kind":"block","code":"background-color: --screenPx(var(--vidMode), var(--ci), round(down, var(--__1mc383395) / 256), var(--__1mc377459), var(--__1mc378087), 3, 8, 128, var(--vidPal));"}],"trailer":"}","folded":true},{"kind":"decl","code":".motherboard #p39581 {","children":[{"kind":"decl","code":"--ci:","children":[{"kind":"value","code":"round(down, var(--__1mc347470) / 256);"}]},{"kind":"block","code":"background-color: --screenPx(var(--vidMode), var(--ci), round(down, var(--__1mc383395) / 256), var(--__1mc377459), var(--__1mc378087), 3, 4, 32, var(--vidPal));"}],"trailer":"}","folded":true},{"kind":"decl","code":".motherboard #p39582 {","children":[{"kind":"decl","code":"--ci:","children":[{"kind":"value","code":"mod(var(--__1mc347471), 256);"}]},{"kind":"block","code":"background-color: --screenPx(var(--vidMode), var(--ci), round(down, var(--__1mc383395) / 256), var(--__1mc377459), var(--__1mc378087), 3, 2, 8, var(--vidPal));"}],"trailer":"}","folded":true},{"kind":"decl","code":".motherboard #p39583 {","children":[{"kind":"decl","code":"--ci:","children":[{"kind":"value","code":"round(down, var(--__1mc347471) / 256);"}]},{"kind":"block","code":"background-color: --screenPx(var(--vidMode), var(--ci), round(down, var(--__1mc383395) / 256), var(--__1mc377459), var(--__1mc378087), 3, 1, 2, var(--vidPal));"}],"trailer":"}","folded":true},{"kind":"decl","code":".motherboard #p39584 {","children":[{"kind":"decl","code":"--ci:","children":[{"kind":"value","code":"mod(var(--__1mc347472), 256);"}]},{"kind":"block","code":"background-color: --screenPx(var(--vidMode), var(--ci), mod(var(--__1mc383396), 256), var(--__1mc377460), var(--__1mc378088), 3, 128, 128, var(--vidPal));"}],"trailer":"}","folded":true},{"kind":"decl","code":".motherboard #p39585 {","children":[{"kind":"decl","code":"--ci:","children":[{"kind":"value","code":"round(down, var(--__1mc347472) / 256);"}]},{"kind":"block","code":"background-color: --screenPx(var(--vidMode), var(--ci), mod(var(--__1mc383396), 256), var(--__1mc377460), var(--__1mc378088), 3, 64, 32, var(--vidPal));"}],"trailer":"}","folded":true},{"kind":"decl","code":".motherboard #p39586 {","children":[{"kind":"decl","code":"--ci:","children":[{"kind":"value","code":"mod(var(--__1mc347473), 256);"}]},{"kind":"block","code":"background-color: --screenPx(var(--vidMode), var(--ci), mod(var(--__1mc383396), 256), var(--__1mc377460), var(--__1mc378088), 3, 32, 8, var(--vidPal));"}],"trailer":"}","folded":true},{"kind":"decl","code":".motherboard #p39587 {","children":[{"kind":"decl","code":"--ci:","children":[{"kind":"value","code":"round(down, var(--__1mc347473) / 256);"}]},{"kind":"block","code":"background-color: --screenPx(var(--vidMode), var(--ci), mod(var(--__1mc383396), 256), var(--__1mc377460), var(--__1mc378088), 3, 16, 2, var(--vidPal));"}],"trailer":"}","folded":true},{"kind":"decl","code":".motherboard #p39588 {","children":[{"kind":"decl","code":"--ci:","children":[{"kind":"value","code":"mod(var(--__1mc347474), 256);"}]},{"kind":"block","code":"background-color: --screenPx(var(--vidMode), var(--ci), round(down, var(--__1mc383396) / 256), var(--__1mc377460), var(--__1mc378089), 3, 8, 128, var(--vidPal));"}],"trailer":"}","folded":true},{"kind":"decl","code":".motherboard #p39589 {","children":[{"kind":"decl","code":"--ci:","children":[{"kind":"value","code":"round(down, var(--__1mc347474) / 256);"}]},{"kind":"block","code":"background-color: --screenPx(var(--vidMode), var(--ci), round(down, var(--__1mc383396) / 256), var(--__1mc377460), var(--__1mc378089), 3, 4, 32, var(--vidPal));"}],"trailer":"}","folded":true},{"kind":"decl","code":".motherboard #p39590 {","children":[{"kind":"decl","code":"--ci:","children":[{"kind":"value","code":"mod(var(--__1mc347475), 256);"}]},{"kind":"block","code":"background-color: --screenPx(var(--vidMode), var(--ci), round(down, var(--__1mc383396) / 256), var(--__1mc377460), var(--__1mc378089), 3, 2, 8, var(--vidPal));"}],"trailer":"}","folded":true},{"kind":"decl","code":".motherboard #p39591 {","children":[{"kind":"decl","code":"--ci:","children":[{"kind":"value","code":"round(down, var(--__1mc347475) / 256);"}]},{"kind":"block","code":"background-color: --screenPx(var(--vidMode), var(--ci), round(down, var(--__1mc383396) / 256), var(--__1mc377460), var(--__1mc378089), 3, 1, 2, var(--vidPal));"}],"trailer":"}","folded":true},{"kind":"decl","code":".motherboard #p39592 {","children":[{"kind":"decl","code":"--ci:","children":[{"kind":"value","code":"mod(var(--__1mc347476), 256);"}]},{"kind":"block","code":"background-color: --screenPx(var(--vidMode), var(--ci), mod(var(--__1mc383397), 256), var(--__1mc377461), var(--__1mc378090), 3, 128, 128, var(--vidPal));"}],"trailer":"}","folded":true},{"kind":"decl","code":".motherboard #p39593 {","children":[{"kind":"decl","code":"--ci:","children":[{"kind":"value","code":"round(down, var(--__1mc347476) / 256);"}]},{"kind":"block","code":"background-color: --screenPx(var(--vidMode), var(--ci), mod(var(--__1mc383397), 256), var(--__1mc377461), var(--__1mc378090), 3, 64, 32, var(--vidPal));"}],"trailer":"}","folded":true},{"kind":"decl","code":".motherboard #p39594 {","children":[{"kind":"decl","code":"--ci:","children":[{"kind":"value","code":"mod(var(--__1mc347477), 256);"}]},{"kind":"block","code":"background-color: --screenPx(var(--vidMode), var(--ci), mod(var(--__1mc383397), 256), var(--__1mc377461), var(--__1mc378090), 3, 32, 8, var(--vidPal));"}],"trailer":"}","folded":true},{"kind":"decl","code":".motherboard #p39595 {","children":[{"kind":"decl","code":"--ci:","children":[{"kind":"value","code":"round(down, var(--__1mc347477) / 256);"}]},{"kind":"block","code":"background-color: --screenPx(var(--vidMode), var(--ci), mod(var(--__1mc383397), 256), var(--__1mc377461), var(--__1mc378090), 3, 16, 2, var(--vidPal));"}],"trailer":"}","folded":true},{"kind":"decl","code":".motherboard #p39596 {","children":[{"kind":"decl","code":"--ci:","children":[{"kind":"value","code":"mod(var(--__1mc347478), 256);"}]},{"kind":"block","code":"background-color: --screenPx(var(--vidMode), var(--ci), round(down, var(--__1mc383397) / 256), var(--__1mc377461), var(--__1mc378091), 3, 8, 128, var(--vidPal));"}],"trailer":"}","folded":true},{"kind":"decl","code":".motherboard #p39597 {","children":[{"kind":"decl","code":"--ci:","children":[{"kind":"value","code":"round(down, var(--__1mc347478) / 256);"}]},{"kind":"block","code":"background-color: --screenPx(var(--vidMode), var(--ci), round(down, var(--__1mc383397) / 256), var(--__1mc377461), var(--__1mc378091), 3, 4, 32, var(--vidPal));"}],"trailer":"}","folded":true},{"kind":"decl","code":".motherboard #p39598 {","children":[{"kind":"decl","code":"--ci:","children":[{"kind":"value","code":"mod(var(--__1mc347479), 256);"}]},{"kind":"block","code":"background-color: --screenPx(var(--vidMode), var(--ci), round(down, var(--__1mc383397) / 256), var(--__1mc377461), var(--__1mc378091), 3, 2, 8, var(--vidPal));"}],"trailer":"}","folded":true},{"kind":"decl","code":".motherboard #p39599 {","children":[{"kind":"decl","code":"--ci:","children":[{"kind":"value","code":"round(down, var(--__1mc347479) / 256);"}]},{"kind":"block","code":"background-color: --screenPx(var(--vidMode), var(--ci), round(down, var(--__1mc383397) / 256), var(--__1mc377461), var(--__1mc378091), 3, 1, 2, var(--vidPal));"}],"trailer":"}","folded":true},{"kind":"decl","code":".motherboard #p39600 {","children":[{"kind":"decl","code":"--ci:","children":[{"kind":"value","code":"mod(var(--__1mc347480), 256);"}]},{"kind":"block","code":"background-color: --screenPx(var(--vidMode), var(--ci), mod(var(--__1mc383398), 256), var(--__1mc377462), var(--__1mc378092), 3, 128, 128, var(--vidPal));"}],"trailer":"}","folded":true},{"kind":"decl","code":".motherboard #p39601 {","children":[{"kind":"decl","code":"--ci:","children":[{"kind":"value","code":"round(down, var(--__1mc347480) / 256);"}]},{"kind":"block","code":"background-color: --screenPx(var(--vidMode), var(--ci), mod(var(--__1mc383398), 256), var(--__1mc377462), var(--__1mc378092), 3, 64, 32, var(--vidPal));"}],"trailer":"}","folded":true},{"kind":"decl","code":".motherboard #p39602 {","children":[{"kind":"decl","code":"--ci:","children":[{"kind":"value","code":"mod(var(--__1mc347481), 256);"}]},{"kind":"block","code":"background-color: --screenPx(var(--vidMode), var(--ci), mod(var(--__1mc383398), 256), var(--__1mc377462), var(--__1mc378092), 3, 32, 8, var(--vidPal));"}],"trailer":"}","folded":true},{"kind":"decl","code":".motherboard #p39603 {","children":[{"kind":"decl","code":"--ci:","children":[{"kind":"value","code":"round(down, var(--__1mc347481) / 256);"}]},{"kind":"block","code":"background-color: --screenPx(var(--vidMode), var(--ci), mod(var(--__1mc383398), 256), var(--__1mc377462), var(--__1mc378092), 3, 16, 2, var(--vidPal));"}],"trailer":"}","folded":true},{"kind":"decl","code":".motherboard #p39604 {","children":[{"kind":"decl","code":"--ci:","children":[{"kind":"value","code":"mod(var(--__1mc347482), 256);"}]},{"kind":"block","code":"background-color: --screenPx(var(--vidMode), var(--ci), round(down, var(--__1mc383398) / 256), var(--__1mc377462), var(--__1mc378093), 3, 8, 128, var(--vidPal));"}],"trailer":"}","folded":true},{"kind":"decl","code":".motherboard #p39605 {","children":[{"kind":"decl","code":"--ci:","children":[{"kind":"value","code":"round(down, var(--__1mc347482) / 256);"}]},{"kind":"block","code":"background-color: --screenPx(var(--vidMode), var(--ci), round(down, var(--__1mc383398) / 256), var(--__1mc377462), var(--__1mc378093), 3, 4, 32, var(--vidPal));"}],"trailer":"}","folded":true},{"kind":"decl","code":".motherboard #p39606 {","children":[{"kind":"decl","code":"--ci:","children":[{"kind":"value","code":"mod(var(--__1mc347483), 256);"}]},{"kind":"block","code":"background-color: --screenPx(var(--vidMode), var(--ci), round(down, var(--__1mc383398) / 256), var(--__1mc377462), var(--__1mc378093), 3, 2, 8, var(--vidPal));"}],"trailer":"}","folded":true},{"kind":"decl","code":".motherboard #p39607 {","children":[{"kind":"decl","code":"--ci:","children":[{"kind":"value","code":"round(down, var(--__1mc347483) / 256);"}]},{"kind":"block","code":"background-color: --screenPx(var(--vidMode), var(--ci), round(down, var(--__1mc383398) / 256), var(--__1mc377462), var(--__1mc378093), 3, 1, 2, var(--vidPal));"}],"trailer":"}","folded":true},{"kind":"decl","code":".motherboard #p39608 {","children":[{"kind":"decl","code":"--ci:","children":[{"kind":"value","code":"mod(var(--__1mc347484), 256);"}]},{"kind":"block","code":"background-color: --screenPx(var(--vidMode), var(--ci), mod(var(--__1mc383399), 256), var(--__1mc377463), var(--__1mc378094), 3, 128, 128, var(--vidPal));"}],"trailer":"}","folded":true},{"kind":"decl","code":".motherboard #p39609 {","children":[{"kind":"decl","code":"--ci:","children":[{"kind":"value","code":"round(down, var(--__1mc347484) / 256);"}]},{"kind":"block","code":"background-color: --screenPx(var(--vidMode), var(--ci), mod(var(--__1mc383399), 256), var(--__1mc377463), var(--__1mc378094), 3, 64, 32, var(--vidPal));"}],"trailer":"}","folded":true},{"kind":"decl","code":".motherboard #p39610 {","children":[{"kind":"decl","code":"--ci:","children":[{"kind":"value","code":"mod(var(--__1mc347485), 256);"}]},{"kind":"block","code":"background-color: --screenPx(var(--vidMode), var(--ci), mod(var(--__1mc383399), 256), var(--__1mc377463), var(--__1mc378094), 3, 32, 8, var(--vidPal));"}],"trailer":"}","folded":true},{"kind":"decl","code":".motherboard #p39611 {","children":[{"kind":"decl","code":"--ci:","children":[{"kind":"value","code":"round(down, var(--__1mc347485) / 256);"}]},{"kind":"block","code":"background-color: --screenPx(var(--vidMode), var(--ci), mod(var(--__1mc383399), 256), var(--__1mc377463), var(--__1mc378094), 3, 16, 2, var(--vidPal));"}],"trailer":"}","folded":true},{"kind":"decl","code":".motherboard #p39612 {","children":[{"kind":"decl","code":"--ci:","children":[{"kind":"value","code":"mod(var(--__1mc347486), 256);"}]},{"kind":"block","code":"background-color: --screenPx(var(--vidMode), var(--ci), round(down, var(--__1mc383399) / 256), var(--__1mc377463), var(--__1mc378095), 3, 8, 128, var(--vidPal));"}],"trailer":"}","folded":true},{"kind":"decl","code":".motherboard #p39613 {","children":[{"kind":"decl","code":"--ci:","children":[{"kind":"value","code":"round(down, var(--__1mc347486) / 256);"}]},{"kind":"block","code":"background-color: --screenPx(var(--vidMode), var(--ci), round(down, var(--__1mc383399) / 256), var(--__1mc377463), var(--__1mc378095), 3, 4, 32, var(--vidPal));"}],"trailer":"}","folded":true},{"kind":"decl","code":".motherboard #p39614 {","children":[{"kind":"decl","code":"--ci:","children":[{"kind":"value","code":"mod(var(--__1mc347487), 256);"}]},{"kind":"block","code":"background-color: --screenPx(var(--vidMode), var(--ci), round(down, var(--__1mc383399) / 256), var(--__1mc377463), var(--__1mc378095), 3, 2, 8, var(--vidPal));"}],"trailer":"}","folded":true},{"kind":"decl","code":".motherboard #p39615 {","children":[{"kind":"decl","code":"--ci:","children":[{"kind":"value","code":"round(down, var(--__1mc347487) / 256);"}]},{"kind":"block","code":"background-color: --screenPx(var(--vidMode), var(--ci), round(down, var(--__1mc383399) / 256), var(--__1mc377463), var(--__1mc378095), 3, 1, 2, var(--vidPal));"}],"trailer":"}","folded":true},{"kind":"decl","code":".motherboard #p39616 {","children":[{"kind":"decl","code":"--ci:","children":[{"kind":"value","code":"mod(var(--__1mc347488), 256);"}]},{"kind":"block","code":"background-color: --screenPx(var(--vidMode), var(--ci), mod(var(--__1mc383400), 256), var(--__1mc377464), var(--__1mc378096), 3, 128, 128, var(--vidPal));"}],"trailer":"}","folded":true},{"kind":"decl","code":".motherboard #p39617 {","children":[{"kind":"decl","code":"--ci:","children":[{"kind":"value","code":"round(down, var(--__1mc347488) / 256);"}]},{"kind":"block","code":"background-color: --screenPx(var(--vidMode), var(--ci), mod(var(--__1mc383400), 256), var(--__1mc377464), var(--__1mc378096), 3, 64, 32, var(--vidPal));"}],"trailer":"}","folded":true},{"kind":"decl","code":".motherboard #p39618 {","children":[{"kind":"decl","code":"--ci:","children":[{"kind":"value","code":"mod(var(--__1mc347489), 256);"}]},{"kind":"block","code":"background-color: --screenPx(var(--vidMode), var(--ci), mod(var(--__1mc383400), 256), var(--__1mc377464), var(--__1mc378096), 3, 32, 8, var(--vidPal));"}],"trailer":"}","folded":true},{"kind":"decl","code":".motherboard #p39619 {","children":[{"kind":"decl","code":"--ci:","children":[{"kind":"value","code":"round(down, var(--__1mc347489) / 256);"}]},{"kind":"block","code":"background-color: --screenPx(var(--vidMode), var(--ci), mod(var(--__1mc383400), 256), var(--__1mc377464), var(--__1mc378096), 3, 16, 2, var(--vidPal));"}],"trailer":"}","folded":true},{"kind":"decl","code":".motherboard #p39620 {","children":[{"kind":"decl","code":"--ci:","children":[{"kind":"value","code":"mod(var(--__1mc347490), 256);"}]},{"kind":"block","code":"background-color: --screenPx(var(--vidMode), var(--ci), round(down, var(--__1mc383400) / 256), var(--__1mc377464), var(--__1mc378097), 3, 8, 128, var(--vidPal));"}],"trailer":"}","folded":true},{"kind":"decl","code":".motherboard #p39621 {","children":[{"kind":"decl","code":"--ci:","children":[{"kind":"value","code":"round(down, var(--__1mc347490) / 256);"}]},{"kind":"block","code":"background-color: --screenPx(var(--vidMode), var(--ci), round(down, var(--__1mc383400) / 256), var(--__1mc377464), var(--__1mc378097), 3, 4, 32, var(--vidPal));"}],"trailer":"}","folded":true},{"kind":"decl","code":".motherboard #p39622 {","children":[{"kind":"decl","code":"--ci:","children":[{"kind":"value","code":"mod(var(--__1mc347491), 256);"}]},{"kind":"block","code":"background-color: --screenPx(var(--vidMode), var(--ci), round(down, var(--__1mc383400) / 256), var(--__1mc377464), var(--__1mc378097), 3, 2, 8, var(--vidPal));"}],"trailer":"}","folded":true},{"kind":"decl","code":".motherboard #p39623 {","children":[{"kind":"decl","code":"--ci:","children":[{"kind":"value","code":"round(down, var(--__1mc347491) / 256);"}]},{"kind":"block","code":"background-color: --screenPx(var(--vidMode), var(--ci), round(down, var(--__1mc383400) / 256), var(--__1mc377464), var(--__1mc378097), 3, 1, 2, var(--vidPal));"}],"trailer":"}","folded":true},{"kind":"decl","code":".motherboard #p39624 {","children":[{"kind":"decl","code":"--ci:","children":[{"kind":"value","code":"mod(var(--__1mc347492), 256);"}]},{"kind":"block","code":"background-color: --screenPx(var(--vidMode), var(--ci), mod(var(--__1mc383401), 256), var(--__1mc377465), var(--__1mc378098), 3, 128, 128, var(--vidPal));"}],"trailer":"}","folded":true},{"kind":"decl","code":".motherboard #p39625 {","children":[{"kind":"decl","code":"--ci:","children":[{"kind":"value","code":"round(down, var(--__1mc347492) / 256);"}]},{"kind":"block","code":"background-color: --screenPx(var(--vidMode), var(--ci), mod(var(--__1mc383401), 256), var(--__1mc377465), var(--__1mc378098), 3, 64, 32, var(--vidPal));"}],"trailer":"}","folded":true},{"kind":"decl","code":".motherboard #p39626 {","children":[{"kind":"decl","code":"--ci:","children":[{"kind":"value","code":"mod(var(--__1mc347493), 256);"}]},{"kind":"block","code":"background-color: --screenPx(var(--vidMode), var(--ci), mod(var(--__1mc383401), 256), var(--__1mc377465), var(--__1mc378098), 3, 32, 8, var(--vidPal));"}],"trailer":"}","folded":true},{"kind":"decl","code":".motherboard #p39627 {","children":[{"kind":"decl","code":"--ci:","children":[{"kind":"value","code":"round(down, var(--__1mc347493) / 256);"}]},{"kind":"block","code":"background-color: --screenPx(var(--vidMode), var(--ci), mod(var(--__1mc383401), 256), var(--__1mc377465), var(--__1mc378098), 3, 16, 2, var(--vidPal));"}],"trailer":"}","folded":true},{"kind":"decl","code":".motherboard #p39628 {","children":[{"kind":"decl","code":"--ci:","children":[{"kind":"value","code":"mod(var(--__1mc347494), 256);"}]},{"kind":"block","code":"background-color: --screenPx(var(--vidMode), var(--ci), round(down, var(--__1mc383401) / 256), var(--__1mc377465), var(--__1mc378099), 3, 8, 128, var(--vidPal));"}],"trailer":"}","folded":true},{"kind":"decl","code":".motherboard #p39629 {","children":[{"kind":"decl","code":"--ci:","children":[{"kind":"value","code":"round(down, var(--__1mc347494) / 256);"}]},{"kind":"block","code":"background-color: --screenPx(var(--vidMode), var(--ci), round(down, var(--__1mc383401) / 256), var(--__1mc377465), var(--__1mc378099), 3, 4, 32, var(--vidPal));"}],"trailer":"}","folded":true},{"kind":"decl","code":".motherboard #p39630 {","children":[{"kind":"decl","code":"--ci:","children":[{"kind":"value","code":"mod(var(--__1mc347495), 256);"}]},{"kind":"block","code":"background-color: --screenPx(var(--vidMode), var(--ci), round(down, var(--__1mc383401) / 256), var(--__1mc377465), var(--__1mc378099), 3, 2, 8, var(--vidPal));"}],"trailer":"}","folded":true},{"kind":"decl","code":".motherboard #p39631 {","children":[{"kind":"decl","code":"--ci:","children":[{"kind":"value","code":"round(down, var(--__1mc347495) / 256);"}]},{"kind":"block","code":"background-color: --screenPx(var(--vidMode), var(--ci), round(down, var(--__1mc383401) / 256), var(--__1mc377465), var(--__1mc378099), 3, 1, 2, var(--vidPal));"}],"trailer":"}","folded":true}],"next":{"ref":"screen/314","remaining":24368}}