{"nodes":[{"kind":"block","code":"/* ===== PROPERTY DECLARATIONS ===== */"},{"kind":"block","code":"/* Below: 1536 @property declarations (one per memory byte),\n   followed by memory read/write rules, the disk, and the clock.\n   The CPU logic above is a small fraction of this file. The rest is memory. */"},{"kind":"block","code":"/* platform wires: the clock heartbeat + the player's keyboard bridge */"},{"kind":"block","code":"@property --clock {\n  syntax: '<integer>';\n  inherits: true;\n  initial-value: 0;\n}","folded":true},{"kind":"block","code":"@property --keyboard {\n  syntax: '<integer>';\n  inherits: true;\n  initial-value: 0;\n}","folded":true},{"kind":"block","code":"@property --kbdHold {\n  syntax: '<integer>';\n  inherits: true;\n  initial-value: 0;\n}","folded":true},{"kind":"block","code":"/* machine state: registers, chipset latches, execution bookkeeping.\n   initial-value is the power-on state (CS:IP starts at the BIOS entry). */"},{"kind":"block","code":"@property --AX {\n  syntax: '<integer>';\n  inherits: true;\n  initial-value: 0;\n}","folded":true},{"kind":"block","code":"@property --CX {\n  syntax: '<integer>';\n  inherits: true;\n  initial-value: 0;\n}","folded":true},{"kind":"block","code":"@property --DX {\n  syntax: '<integer>';\n  inherits: true;\n  initial-value: 0;\n}","folded":true},{"kind":"block","code":"@property --BX {\n  syntax: '<integer>';\n  inherits: true;\n  initial-value: 0;\n}","folded":true},{"kind":"block","code":"@property --SP {\n  syntax: '<integer>';\n  inherits: true;\n  initial-value: 1528;\n}","folded":true},{"kind":"block","code":"@property --BP {\n  syntax: '<integer>';\n  inherits: true;\n  initial-value: 0;\n}","folded":true},{"kind":"block","code":"@property --SI {\n  syntax: '<integer>';\n  inherits: true;\n  initial-value: 0;\n}","folded":true},{"kind":"block","code":"@property --DI {\n  syntax: '<integer>';\n  inherits: true;\n  initial-value: 0;\n}","folded":true},{"kind":"block","code":"@property --CS {\n  syntax: '<integer>';\n  inherits: true;\n  initial-value: 0;\n}","folded":true},{"kind":"block","code":"@property --DS {\n  syntax: '<integer>';\n  inherits: true;\n  initial-value: 0;\n}","folded":true},{"kind":"block","code":"@property --ES {\n  syntax: '<integer>';\n  inherits: true;\n  initial-value: 0;\n}","folded":true},{"kind":"block","code":"@property --SS {\n  syntax: '<integer>';\n  inherits: true;\n  initial-value: 0;\n}","folded":true},{"kind":"block","code":"@property --IP {\n  syntax: '<integer>';\n  inherits: true;\n  initial-value: 256;\n}","folded":true},{"kind":"block","code":"@property --flags {\n  syntax: '<integer>';\n  inherits: true;\n  initial-value: 2;\n}","folded":true},{"kind":"block","code":"@property --halt {\n  syntax: '<integer>';\n  inherits: true;\n  initial-value: 0;\n}","folded":true},{"kind":"block","code":"@property --cycleCount {\n  syntax: '<integer>';\n  inherits: true;\n  initial-value: 0;\n}","folded":true},{"kind":"block","code":"@property --_tfPending {\n  syntax: '<integer>';\n  inherits: true;\n  initial-value: 0;\n}","folded":true},{"kind":"block","code":"@property --picMask {\n  syntax: '<integer>';\n  inherits: true;\n  initial-value: 255;\n}","folded":true},{"kind":"block","code":"@property --picPending {\n  syntax: '<integer>';\n  inherits: true;\n  initial-value: 0;\n}","folded":true},{"kind":"block","code":"@property --picInService {\n  syntax: '<integer>';\n  inherits: true;\n  initial-value: 0;\n}","folded":true},{"kind":"block","code":"@property --pitMode {\n  syntax: '<integer>';\n  inherits: true;\n  initial-value: 0;\n}","folded":true},{"kind":"block","code":"@property --pitReload {\n  syntax: '<integer>';\n  inherits: true;\n  initial-value: 0;\n}","folded":true},{"kind":"block","code":"@property --pitCounter {\n  syntax: '<integer>';\n  inherits: true;\n  initial-value: 0;\n}","folded":true},{"kind":"block","code":"@property --pitWriteState {\n  syntax: '<integer>';\n  inherits: true;\n  initial-value: 0;\n}","folded":true},{"kind":"block","code":"@property --prevKeyboard {\n  syntax: '<integer>';\n  inherits: true;\n  initial-value: 0;\n}","folded":true},{"kind":"block","code":"@property --kbdScancodeLatch {\n  syntax: '<integer>';\n  inherits: true;\n  initial-value: 0;\n}","folded":true},{"kind":"block","code":"@property --kbdHeld0 {\n  syntax: '<integer>';\n  inherits: true;\n  initial-value: 0;\n}","folded":true},{"kind":"block","code":"@property --kbdHeld1 {\n  syntax: '<integer>';\n  inherits: true;\n  initial-value: 0;\n}","folded":true},{"kind":"block","code":"@property --kbdHeld2 {\n  syntax: '<integer>';\n  inherits: true;\n  initial-value: 0;\n}","folded":true},{"kind":"block","code":"@property --kbdHeld3 {\n  syntax: '<integer>';\n  inherits: true;\n  initial-value: 0;\n}","folded":true},{"kind":"block","code":"@property --kbdHeld4 {\n  syntax: '<integer>';\n  inherits: true;\n  initial-value: 0;\n}","folded":true},{"kind":"block","code":"@property --kbdHeld5 {\n  syntax: '<integer>';\n  inherits: true;\n  initial-value: 0;\n}","folded":true},{"kind":"block","code":"@property --kbdHeld6 {\n  syntax: '<integer>';\n  inherits: true;\n  initial-value: 0;\n}","folded":true},{"kind":"block","code":"@property --kbdHeld7 {\n  syntax: '<integer>';\n  inherits: true;\n  initial-value: 0;\n}","folded":true},{"kind":"block","code":"@property --dacWriteIndex {\n  syntax: '<integer>';\n  inherits: true;\n  initial-value: 0;\n}","folded":true},{"kind":"block","code":"@property --dacSubIndex {\n  syntax: '<integer>';\n  inherits: true;\n  initial-value: 0;\n}","folded":true},{"kind":"block","code":"@property --dacReadIndex {\n  syntax: '<integer>';\n  inherits: true;\n  initial-value: 0;\n}","folded":true},{"kind":"block","code":"@property --dacReadSubIndex {\n  syntax: '<integer>';\n  inherits: true;\n  initial-value: 0;\n}","folded":true},{"kind":"block","code":"@property --haltCode {\n  syntax: '<integer>';\n  inherits: true;\n  initial-value: 0;\n}","folded":true},{"kind":"block","code":"/* memory cells: one @property per 2-byte cell (--mcN holds bytes 2N and 2N+1);\n   initial-value = the assembled memory image, so power-on state costs no writes */"},{"kind":"block","code":"@property --mc0 {\n  syntax: '<integer>';\n  inherits: true;\n  initial-value: 0;\n}","folded":true},{"kind":"block","code":"@property --mc1 {\n  syntax: '<integer>';\n  inherits: true;\n  initial-value: 0;\n}","folded":true},{"kind":"block","code":"@property --mc2 {\n  syntax: '<integer>';\n  inherits: true;\n  initial-value: 0;\n}","folded":true},{"kind":"block","code":"@property --mc3 {\n  syntax: '<integer>';\n  inherits: true;\n  initial-value: 0;\n}","folded":true},{"kind":"block","code":"@property --mc4 {\n  syntax: '<integer>';\n  inherits: true;\n  initial-value: 0;\n}","folded":true},{"kind":"block","code":"@property --mc5 {\n  syntax: '<integer>';\n  inherits: true;\n  initial-value: 0;\n}","folded":true},{"kind":"block","code":"@property --mc6 {\n  syntax: '<integer>';\n  inherits: true;\n  initial-value: 0;\n}","folded":true},{"kind":"block","code":"@property --mc7 {\n  syntax: '<integer>';\n  inherits: true;\n  initial-value: 0;\n}","folded":true},{"kind":"block","code":"@property --mc8 {\n  syntax: '<integer>';\n  inherits: true;\n  initial-value: 0;\n}","folded":true},{"kind":"block","code":"@property --mc9 {\n  syntax: '<integer>';\n  inherits: true;\n  initial-value: 0;\n}","folded":true},{"kind":"block","code":"@property --mc10 {\n  syntax: '<integer>';\n  inherits: true;\n  initial-value: 0;\n}","folded":true},{"kind":"block","code":"@property --mc11 {\n  syntax: '<integer>';\n  inherits: true;\n  initial-value: 0;\n}","folded":true},{"kind":"block","code":"@property --mc12 {\n  syntax: '<integer>';\n  inherits: true;\n  initial-value: 0;\n}","folded":true},{"kind":"block","code":"@property --mc13 {\n  syntax: '<integer>';\n  inherits: true;\n  initial-value: 0;\n}","folded":true},{"kind":"block","code":"@property --mc14 {\n  syntax: '<integer>';\n  inherits: true;\n  initial-value: 0;\n}","folded":true},{"kind":"block","code":"@property --mc15 {\n  syntax: '<integer>';\n  inherits: true;\n  initial-value: 0;\n}","folded":true},{"kind":"block","code":"@property --mc16 {\n  syntax: '<integer>';\n  inherits: true;\n  initial-value: 0;\n}","folded":true},{"kind":"block","code":"@property --mc17 {\n  syntax: '<integer>';\n  inherits: true;\n  initial-value: 0;\n}","folded":true},{"kind":"block","code":"@property --mc18 {\n  syntax: '<integer>';\n  inherits: true;\n  initial-value: 0;\n}","folded":true},{"kind":"block","code":"@property --mc19 {\n  syntax: '<integer>';\n  inherits: true;\n  initial-value: 0;\n}","folded":true},{"kind":"block","code":"@property --mc20 {\n  syntax: '<integer>';\n  inherits: true;\n  initial-value: 0;\n}","folded":true},{"kind":"block","code":"@property --mc21 {\n  syntax: '<integer>';\n  inherits: true;\n  initial-value: 0;\n}","folded":true},{"kind":"block","code":"@property --mc22 {\n  syntax: '<integer>';\n  inherits: true;\n  initial-value: 0;\n}","folded":true},{"kind":"block","code":"@property --mc23 {\n  syntax: '<integer>';\n  inherits: true;\n  initial-value: 0;\n}","folded":true},{"kind":"block","code":"@property --mc24 {\n  syntax: '<integer>';\n  inherits: true;\n  initial-value: 0;\n}","folded":true},{"kind":"block","code":"@property --mc25 {\n  syntax: '<integer>';\n  inherits: true;\n  initial-value: 0;\n}","folded":true},{"kind":"block","code":"@property --mc26 {\n  syntax: '<integer>';\n  inherits: true;\n  initial-value: 0;\n}","folded":true},{"kind":"block","code":"@property --mc27 {\n  syntax: '<integer>';\n  inherits: true;\n  initial-value: 0;\n}","folded":true},{"kind":"block","code":"@property --mc28 {\n  syntax: '<integer>';\n  inherits: true;\n  initial-value: 0;\n}","folded":true},{"kind":"block","code":"@property --mc29 {\n  syntax: '<integer>';\n  inherits: true;\n  initial-value: 0;\n}","folded":true},{"kind":"block","code":"@property --mc30 {\n  syntax: '<integer>';\n  inherits: true;\n  initial-value: 0;\n}","folded":true},{"kind":"block","code":"@property --mc31 {\n  syntax: '<integer>';\n  inherits: true;\n  initial-value: 0;\n}","folded":true},{"kind":"block","code":"@property --mc32 {\n  syntax: '<integer>';\n  inherits: true;\n  initial-value: 0;\n}","folded":true},{"kind":"block","code":"@property --mc33 {\n  syntax: '<integer>';\n  inherits: true;\n  initial-value: 0;\n}","folded":true},{"kind":"block","code":"@property --mc34 {\n  syntax: '<integer>';\n  inherits: true;\n  initial-value: 0;\n}","folded":true},{"kind":"block","code":"@property --mc35 {\n  syntax: '<integer>';\n  inherits: true;\n  initial-value: 0;\n}","folded":true},{"kind":"block","code":"@property --mc36 {\n  syntax: '<integer>';\n  inherits: true;\n  initial-value: 0;\n}","folded":true},{"kind":"block","code":"@property --mc37 {\n  syntax: '<integer>';\n  inherits: true;\n  initial-value: 0;\n}","folded":true},{"kind":"block","code":"@property --mc38 {\n  syntax: '<integer>';\n  inherits: true;\n  initial-value: 0;\n}","folded":true},{"kind":"block","code":"@property --mc39 {\n  syntax: '<integer>';\n  inherits: true;\n  initial-value: 0;\n}","folded":true},{"kind":"block","code":"@property --mc40 {\n  syntax: '<integer>';\n  inherits: true;\n  initial-value: 0;\n}","folded":true},{"kind":"block","code":"@property --mc41 {\n  syntax: '<integer>';\n  inherits: true;\n  initial-value: 0;\n}","folded":true},{"kind":"block","code":"@property --mc42 {\n  syntax: '<integer>';\n  inherits: true;\n  initial-value: 0;\n}","folded":true},{"kind":"block","code":"@property --mc43 {\n  syntax: '<integer>';\n  inherits: true;\n  initial-value: 0;\n}","folded":true},{"kind":"block","code":"@property --mc44 {\n  syntax: '<integer>';\n  inherits: true;\n  initial-value: 0;\n}","folded":true},{"kind":"block","code":"@property --mc45 {\n  syntax: '<integer>';\n  inherits: true;\n  initial-value: 0;\n}","folded":true},{"kind":"block","code":"@property --mc46 {\n  syntax: '<integer>';\n  inherits: true;\n  initial-value: 0;\n}","folded":true},{"kind":"block","code":"@property --mc47 {\n  syntax: '<integer>';\n  inherits: true;\n  initial-value: 0;\n}","folded":true},{"kind":"block","code":"@property --mc48 {\n  syntax: '<integer>';\n  inherits: true;\n  initial-value: 0;\n}","folded":true},{"kind":"block","code":"@property --mc49 {\n  syntax: '<integer>';\n  inherits: true;\n  initial-value: 0;\n}","folded":true},{"kind":"block","code":"@property --mc50 {\n  syntax: '<integer>';\n  inherits: true;\n  initial-value: 0;\n}","folded":true},{"kind":"block","code":"@property --mc51 {\n  syntax: '<integer>';\n  inherits: true;\n  initial-value: 0;\n}","folded":true},{"kind":"block","code":"@property --mc52 {\n  syntax: '<integer>';\n  inherits: true;\n  initial-value: 0;\n}","folded":true},{"kind":"block","code":"@property --mc53 {\n  syntax: '<integer>';\n  inherits: true;\n  initial-value: 0;\n}","folded":true},{"kind":"block","code":"@property --mc54 {\n  syntax: '<integer>';\n  inherits: true;\n  initial-value: 0;\n}","folded":true},{"kind":"block","code":"@property --mc55 {\n  syntax: '<integer>';\n  inherits: true;\n  initial-value: 0;\n}","folded":true},{"kind":"block","code":"@property --mc56 {\n  syntax: '<integer>';\n  inherits: true;\n  initial-value: 0;\n}","folded":true},{"kind":"block","code":"@property --mc57 {\n  syntax: '<integer>';\n  inherits: true;\n  initial-value: 0;\n}","folded":true},{"kind":"block","code":"@property --mc58 {\n  syntax: '<integer>';\n  inherits: true;\n  initial-value: 0;\n}","folded":true},{"kind":"block","code":"@property --mc59 {\n  syntax: '<integer>';\n  inherits: true;\n  initial-value: 0;\n}","folded":true},{"kind":"block","code":"@property --mc60 {\n  syntax: '<integer>';\n  inherits: true;\n  initial-value: 0;\n}","folded":true},{"kind":"block","code":"@property --mc61 {\n  syntax: '<integer>';\n  inherits: true;\n  initial-value: 0;\n}","folded":true},{"kind":"block","code":"@property --mc62 {\n  syntax: '<integer>';\n  inherits: true;\n  initial-value: 0;\n}","folded":true},{"kind":"block","code":"@property --mc63 {\n  syntax: '<integer>';\n  inherits: true;\n  initial-value: 0;\n}","folded":true},{"kind":"block","code":"@property --mc64 {\n  syntax: '<integer>';\n  inherits: true;\n  initial-value: 0;\n}","folded":true},{"kind":"block","code":"@property --mc65 {\n  syntax: '<integer>';\n  inherits: true;\n  initial-value: 0;\n}","folded":true},{"kind":"block","code":"@property --mc66 {\n  syntax: '<integer>';\n  inherits: true;\n  initial-value: 0;\n}","folded":true},{"kind":"block","code":"@property --mc67 {\n  syntax: '<integer>';\n  inherits: true;\n  initial-value: 0;\n}","folded":true},{"kind":"block","code":"@property --mc68 {\n  syntax: '<integer>';\n  inherits: true;\n  initial-value: 0;\n}","folded":true},{"kind":"block","code":"@property --mc69 {\n  syntax: '<integer>';\n  inherits: true;\n  initial-value: 0;\n}","folded":true},{"kind":"block","code":"@property --mc70 {\n  syntax: '<integer>';\n  inherits: true;\n  initial-value: 0;\n}","folded":true},{"kind":"block","code":"@property --mc71 {\n  syntax: '<integer>';\n  inherits: true;\n  initial-value: 0;\n}","folded":true},{"kind":"block","code":"@property --mc72 {\n  syntax: '<integer>';\n  inherits: true;\n  initial-value: 0;\n}","folded":true},{"kind":"block","code":"@property --mc73 {\n  syntax: '<integer>';\n  inherits: true;\n  initial-value: 0;\n}","folded":true},{"kind":"block","code":"@property --mc74 {\n  syntax: '<integer>';\n  inherits: true;\n  initial-value: 0;\n}","folded":true},{"kind":"block","code":"@property --mc75 {\n  syntax: '<integer>';\n  inherits: true;\n  initial-value: 0;\n}","folded":true},{"kind":"block","code":"@property --mc76 {\n  syntax: '<integer>';\n  inherits: true;\n  initial-value: 0;\n}","folded":true},{"kind":"block","code":"@property --mc77 {\n  syntax: '<integer>';\n  inherits: true;\n  initial-value: 0;\n}","folded":true},{"kind":"block","code":"@property --mc78 {\n  syntax: '<integer>';\n  inherits: true;\n  initial-value: 0;\n}","folded":true},{"kind":"block","code":"@property --mc79 {\n  syntax: '<integer>';\n  inherits: true;\n  initial-value: 0;\n}","folded":true},{"kind":"block","code":"@property --mc80 {\n  syntax: '<integer>';\n  inherits: true;\n  initial-value: 0;\n}","folded":true},{"kind":"block","code":"@property --mc81 {\n  syntax: '<integer>';\n  inherits: true;\n  initial-value: 0;\n}","folded":true},{"kind":"block","code":"@property --mc82 {\n  syntax: '<integer>';\n  inherits: true;\n  initial-value: 0;\n}","folded":true},{"kind":"block","code":"@property --mc83 {\n  syntax: '<integer>';\n  inherits: true;\n  initial-value: 0;\n}","folded":true},{"kind":"block","code":"@property --mc84 {\n  syntax: '<integer>';\n  inherits: true;\n  initial-value: 0;\n}","folded":true},{"kind":"block","code":"@property --mc85 {\n  syntax: '<integer>';\n  inherits: true;\n  initial-value: 0;\n}","folded":true},{"kind":"block","code":"@property --mc86 {\n  syntax: '<integer>';\n  inherits: true;\n  initial-value: 0;\n}","folded":true},{"kind":"block","code":"@property --mc87 {\n  syntax: '<integer>';\n  inherits: true;\n  initial-value: 0;\n}","folded":true},{"kind":"block","code":"@property --mc88 {\n  syntax: '<integer>';\n  inherits: true;\n  initial-value: 0;\n}","folded":true},{"kind":"block","code":"@property --mc89 {\n  syntax: '<integer>';\n  inherits: true;\n  initial-value: 0;\n}","folded":true},{"kind":"block","code":"@property --mc90 {\n  syntax: '<integer>';\n  inherits: true;\n  initial-value: 0;\n}","folded":true},{"kind":"block","code":"@property --mc91 {\n  syntax: '<integer>';\n  inherits: true;\n  initial-value: 0;\n}","folded":true},{"kind":"block","code":"@property --mc92 {\n  syntax: '<integer>';\n  inherits: true;\n  initial-value: 0;\n}","folded":true},{"kind":"block","code":"@property --mc93 {\n  syntax: '<integer>';\n  inherits: true;\n  initial-value: 0;\n}","folded":true},{"kind":"block","code":"@property --mc94 {\n  syntax: '<integer>';\n  inherits: true;\n  initial-value: 0;\n}","folded":true},{"kind":"block","code":"@property --mc95 {\n  syntax: '<integer>';\n  inherits: true;\n  initial-value: 0;\n}","folded":true},{"kind":"block","code":"@property --mc96 {\n  syntax: '<integer>';\n  inherits: true;\n  initial-value: 0;\n}","folded":true},{"kind":"block","code":"@property --mc97 {\n  syntax: '<integer>';\n  inherits: true;\n  initial-value: 0;\n}","folded":true},{"kind":"block","code":"@property --mc98 {\n  syntax: '<integer>';\n  inherits: true;\n  initial-value: 0;\n}","folded":true},{"kind":"block","code":"@property --mc99 {\n  syntax: '<integer>';\n  inherits: true;\n  initial-value: 0;\n}","folded":true},{"kind":"block","code":"@property --mc100 {\n  syntax: '<integer>';\n  inherits: true;\n  initial-value: 0;\n}","folded":true},{"kind":"block","code":"@property --mc101 {\n  syntax: '<integer>';\n  inherits: true;\n  initial-value: 0;\n}","folded":true},{"kind":"block","code":"@property --mc102 {\n  syntax: '<integer>';\n  inherits: true;\n  initial-value: 0;\n}","folded":true},{"kind":"block","code":"@property --mc103 {\n  syntax: '<integer>';\n  inherits: true;\n  initial-value: 0;\n}","folded":true},{"kind":"block","code":"@property --mc104 {\n  syntax: '<integer>';\n  inherits: true;\n  initial-value: 0;\n}","folded":true},{"kind":"block","code":"@property --mc105 {\n  syntax: '<integer>';\n  inherits: true;\n  initial-value: 0;\n}","folded":true},{"kind":"block","code":"@property --mc106 {\n  syntax: '<integer>';\n  inherits: true;\n  initial-value: 0;\n}","folded":true},{"kind":"block","code":"@property --mc107 {\n  syntax: '<integer>';\n  inherits: true;\n  initial-value: 0;\n}","folded":true},{"kind":"block","code":"@property --mc108 {\n  syntax: '<integer>';\n  inherits: true;\n  initial-value: 0;\n}","folded":true},{"kind":"block","code":"@property --mc109 {\n  syntax: '<integer>';\n  inherits: true;\n  initial-value: 0;\n}","folded":true},{"kind":"block","code":"@property --mc110 {\n  syntax: '<integer>';\n  inherits: true;\n  initial-value: 0;\n}","folded":true},{"kind":"block","code":"@property --mc111 {\n  syntax: '<integer>';\n  inherits: true;\n  initial-value: 0;\n}","folded":true},{"kind":"block","code":"@property --mc112 {\n  syntax: '<integer>';\n  inherits: true;\n  initial-value: 0;\n}","folded":true},{"kind":"block","code":"@property --mc113 {\n  syntax: '<integer>';\n  inherits: true;\n  initial-value: 0;\n}","folded":true},{"kind":"block","code":"@property --mc114 {\n  syntax: '<integer>';\n  inherits: true;\n  initial-value: 0;\n}","folded":true},{"kind":"block","code":"@property --mc115 {\n  syntax: '<integer>';\n  inherits: true;\n  initial-value: 0;\n}","folded":true},{"kind":"block","code":"@property --mc116 {\n  syntax: '<integer>';\n  inherits: true;\n  initial-value: 0;\n}","folded":true},{"kind":"block","code":"@property --mc117 {\n  syntax: '<integer>';\n  inherits: true;\n  initial-value: 0;\n}","folded":true},{"kind":"block","code":"@property --mc118 {\n  syntax: '<integer>';\n  inherits: true;\n  initial-value: 0;\n}","folded":true},{"kind":"block","code":"@property --mc119 {\n  syntax: '<integer>';\n  inherits: true;\n  initial-value: 0;\n}","folded":true},{"kind":"block","code":"@property --mc120 {\n  syntax: '<integer>';\n  inherits: true;\n  initial-value: 0;\n}","folded":true},{"kind":"block","code":"@property --mc121 {\n  syntax: '<integer>';\n  inherits: true;\n  initial-value: 0;\n}","folded":true},{"kind":"block","code":"@property --mc122 {\n  syntax: '<integer>';\n  inherits: true;\n  initial-value: 0;\n}","folded":true},{"kind":"block","code":"@property --mc123 {\n  syntax: '<integer>';\n  inherits: true;\n  initial-value: 0;\n}","folded":true},{"kind":"block","code":"@property --mc124 {\n  syntax: '<integer>';\n  inherits: true;\n  initial-value: 0;\n}","folded":true},{"kind":"block","code":"@property --mc125 {\n  syntax: '<integer>';\n  inherits: true;\n  initial-value: 0;\n}","folded":true},{"kind":"block","code":"@property --mc126 {\n  syntax: '<integer>';\n  inherits: true;\n  initial-value: 0;\n}","folded":true},{"kind":"block","code":"@property --mc127 {\n  syntax: '<integer>';\n  inherits: true;\n  initial-value: 0;\n}","folded":true},{"kind":"block","code":"@property --mc128 {\n  syntax: '<integer>';\n  inherits: true;\n  initial-value: 1464;\n}","folded":true},{"kind":"block","code":"@property --mc129 {\n  syntax: '<integer>';\n  inherits: true;\n  initial-value: 52480;\n}","folded":true},{"kind":"block","code":"@property --mc130 {\n  syntax: '<integer>';\n  inherits: true;\n  initial-value: 32;\n}","folded":true},{"kind":"block","code":"@property --mc131 {\n  syntax: '<integer>';\n  inherits: true;\n  initial-value: 0;\n}","folded":true},{"kind":"block","code":"@property --mc132 {\n  syntax: '<integer>';\n  inherits: true;\n  initial-value: 0;\n}","folded":true},{"kind":"block","code":"@property --mc133 {\n  syntax: '<integer>';\n  inherits: true;\n  initial-value: 0;\n}","folded":true},{"kind":"block","code":"@property --mc134 {\n  syntax: '<integer>';\n  inherits: true;\n  initial-value: 0;\n}","folded":true},{"kind":"block","code":"@property --mc135 {\n  syntax: '<integer>';\n  inherits: true;\n  initial-value: 0;\n}","folded":true},{"kind":"block","code":"@property --mc136 {\n  syntax: '<integer>';\n  inherits: true;\n  initial-value: 0;\n}","folded":true},{"kind":"block","code":"@property --mc137 {\n  syntax: '<integer>';\n  inherits: true;\n  initial-value: 0;\n}","folded":true},{"kind":"block","code":"@property --mc138 {\n  syntax: '<integer>';\n  inherits: true;\n  initial-value: 0;\n}","folded":true},{"kind":"block","code":"@property --mc139 {\n  syntax: '<integer>';\n  inherits: true;\n  initial-value: 0;\n}","folded":true},{"kind":"block","code":"@property --mc140 {\n  syntax: '<integer>';\n  inherits: true;\n  initial-value: 0;\n}","folded":true},{"kind":"block","code":"@property --mc141 {\n  syntax: '<integer>';\n  inherits: true;\n  initial-value: 0;\n}","folded":true},{"kind":"block","code":"@property --mc142 {\n  syntax: '<integer>';\n  inherits: true;\n  initial-value: 0;\n}","folded":true},{"kind":"block","code":"@property --mc143 {\n  syntax: '<integer>';\n  inherits: true;\n  initial-value: 0;\n}","folded":true},{"kind":"block","code":"@property --mc144 {\n  syntax: '<integer>';\n  inherits: true;\n  initial-value: 0;\n}","folded":true},{"kind":"block","code":"@property --mc145 {\n  syntax: '<integer>';\n  inherits: true;\n  initial-value: 0;\n}","folded":true},{"kind":"block","code":"@property --mc146 {\n  syntax: '<integer>';\n  inherits: true;\n  initial-value: 0;\n}","folded":true},{"kind":"block","code":"@property --mc147 {\n  syntax: '<integer>';\n  inherits: true;\n  initial-value: 0;\n}","folded":true},{"kind":"block","code":"@property --mc148 {\n  syntax: '<integer>';\n  inherits: true;\n  initial-value: 0;\n}","folded":true},{"kind":"block","code":"@property --mc149 {\n  syntax: '<integer>';\n  inherits: true;\n  initial-value: 0;\n}","folded":true},{"kind":"block","code":"@property --mc150 {\n  syntax: '<integer>';\n  inherits: true;\n  initial-value: 0;\n}","folded":true},{"kind":"block","code":"@property --mc151 {\n  syntax: '<integer>';\n  inherits: true;\n  initial-value: 0;\n}","folded":true},{"kind":"block","code":"@property --mc152 {\n  syntax: '<integer>';\n  inherits: true;\n  initial-value: 0;\n}","folded":true},{"kind":"block","code":"@property --mc153 {\n  syntax: '<integer>';\n  inherits: true;\n  initial-value: 0;\n}","folded":true},{"kind":"block","code":"@property --mc154 {\n  syntax: '<integer>';\n  inherits: true;\n  initial-value: 0;\n}","folded":true},{"kind":"block","code":"@property --mc155 {\n  syntax: '<integer>';\n  inherits: true;\n  initial-value: 0;\n}","folded":true},{"kind":"block","code":"@property --mc156 {\n  syntax: '<integer>';\n  inherits: true;\n  initial-value: 0;\n}","folded":true},{"kind":"block","code":"@property --mc157 {\n  syntax: '<integer>';\n  inherits: true;\n  initial-value: 0;\n}","folded":true},{"kind":"block","code":"@property --mc158 {\n  syntax: '<integer>';\n  inherits: true;\n  initial-value: 0;\n}","folded":true},{"kind":"block","code":"@property --mc159 {\n  syntax: '<integer>';\n  inherits: true;\n  initial-value: 0;\n}","folded":true},{"kind":"block","code":"@property --mc160 {\n  syntax: '<integer>';\n  inherits: true;\n  initial-value: 0;\n}","folded":true},{"kind":"block","code":"@property --mc161 {\n  syntax: '<integer>';\n  inherits: true;\n  initial-value: 0;\n}","folded":true},{"kind":"block","code":"@property --mc162 {\n  syntax: '<integer>';\n  inherits: true;\n  initial-value: 0;\n}","folded":true},{"kind":"block","code":"@property --mc163 {\n  syntax: '<integer>';\n  inherits: true;\n  initial-value: 0;\n}","folded":true},{"kind":"block","code":"@property --mc164 {\n  syntax: '<integer>';\n  inherits: true;\n  initial-value: 0;\n}","folded":true},{"kind":"block","code":"@property --mc165 {\n  syntax: '<integer>';\n  inherits: true;\n  initial-value: 0;\n}","folded":true},{"kind":"block","code":"@property --mc166 {\n  syntax: '<integer>';\n  inherits: true;\n  initial-value: 0;\n}","folded":true},{"kind":"block","code":"@property --mc167 {\n  syntax: '<integer>';\n  inherits: true;\n  initial-value: 0;\n}","folded":true},{"kind":"block","code":"@property --mc168 {\n  syntax: '<integer>';\n  inherits: true;\n  initial-value: 0;\n}","folded":true},{"kind":"block","code":"@property --mc169 {\n  syntax: '<integer>';\n  inherits: true;\n  initial-value: 0;\n}","folded":true},{"kind":"block","code":"@property --mc170 {\n  syntax: '<integer>';\n  inherits: true;\n  initial-value: 0;\n}","folded":true},{"kind":"block","code":"@property --mc171 {\n  syntax: '<integer>';\n  inherits: true;\n  initial-value: 0;\n}","folded":true},{"kind":"block","code":"@property --mc172 {\n  syntax: '<integer>';\n  inherits: true;\n  initial-value: 0;\n}","folded":true},{"kind":"block","code":"@property --mc173 {\n  syntax: '<integer>';\n  inherits: true;\n  initial-value: 0;\n}","folded":true},{"kind":"block","code":"@property --mc174 {\n  syntax: '<integer>';\n  inherits: true;\n  initial-value: 0;\n}","folded":true},{"kind":"block","code":"@property --mc175 {\n  syntax: '<integer>';\n  inherits: true;\n  initial-value: 0;\n}","folded":true},{"kind":"block","code":"@property --mc176 {\n  syntax: '<integer>';\n  inherits: true;\n  initial-value: 0;\n}","folded":true},{"kind":"block","code":"@property --mc177 {\n  syntax: '<integer>';\n  inherits: true;\n  initial-value: 0;\n}","folded":true},{"kind":"block","code":"@property --mc178 {\n  syntax: '<integer>';\n  inherits: true;\n  initial-value: 0;\n}","folded":true},{"kind":"block","code":"@property --mc179 {\n  syntax: '<integer>';\n  inherits: true;\n  initial-value: 0;\n}","folded":true},{"kind":"block","code":"@property --mc180 {\n  syntax: '<integer>';\n  inherits: true;\n  initial-value: 0;\n}","folded":true},{"kind":"block","code":"@property --mc181 {\n  syntax: '<integer>';\n  inherits: true;\n  initial-value: 0;\n}","folded":true},{"kind":"block","code":"@property --mc182 {\n  syntax: '<integer>';\n  inherits: true;\n  initial-value: 0;\n}","folded":true},{"kind":"block","code":"@property --mc183 {\n  syntax: '<integer>';\n  inherits: true;\n  initial-value: 0;\n}","folded":true},{"kind":"block","code":"@property --mc184 {\n  syntax: '<integer>';\n  inherits: true;\n  initial-value: 0;\n}","folded":true},{"kind":"block","code":"@property --mc185 {\n  syntax: '<integer>';\n  inherits: true;\n  initial-value: 0;\n}","folded":true},{"kind":"block","code":"@property --mc186 {\n  syntax: '<integer>';\n  inherits: true;\n  initial-value: 0;\n}","folded":true},{"kind":"block","code":"@property --mc187 {\n  syntax: '<integer>';\n  inherits: true;\n  initial-value: 0;\n}","folded":true},{"kind":"block","code":"@property --mc188 {\n  syntax: '<integer>';\n  inherits: true;\n  initial-value: 0;\n}","folded":true},{"kind":"block","code":"@property --mc189 {\n  syntax: '<integer>';\n  inherits: true;\n  initial-value: 0;\n}","folded":true},{"kind":"block","code":"@property --mc190 {\n  syntax: '<integer>';\n  inherits: true;\n  initial-value: 0;\n}","folded":true},{"kind":"block","code":"@property --mc191 {\n  syntax: '<integer>';\n  inherits: true;\n  initial-value: 0;\n}","folded":true},{"kind":"block","code":"@property --mc192 {\n  syntax: '<integer>';\n  inherits: true;\n  initial-value: 0;\n}","folded":true},{"kind":"block","code":"@property --mc193 {\n  syntax: '<integer>';\n  inherits: true;\n  initial-value: 0;\n}","folded":true},{"kind":"block","code":"@property --mc194 {\n  syntax: '<integer>';\n  inherits: true;\n  initial-value: 0;\n}","folded":true},{"kind":"block","code":"@property --mc195 {\n  syntax: '<integer>';\n  inherits: true;\n  initial-value: 0;\n}","folded":true},{"kind":"block","code":"@property --mc196 {\n  syntax: '<integer>';\n  inherits: true;\n  initial-value: 0;\n}","folded":true},{"kind":"block","code":"@property --mc197 {\n  syntax: '<integer>';\n  inherits: true;\n  initial-value: 0;\n}","folded":true},{"kind":"block","code":"@property --mc198 {\n  syntax: '<integer>';\n  inherits: true;\n  initial-value: 0;\n}","folded":true},{"kind":"block","code":"@property --mc199 {\n  syntax: '<integer>';\n  inherits: true;\n  initial-value: 0;\n}","folded":true},{"kind":"block","code":"@property --mc200 {\n  syntax: '<integer>';\n  inherits: true;\n  initial-value: 0;\n}","folded":true},{"kind":"block","code":"@property --mc201 {\n  syntax: '<integer>';\n  inherits: true;\n  initial-value: 0;\n}","folded":true},{"kind":"block","code":"@property --mc202 {\n  syntax: '<integer>';\n  inherits: true;\n  initial-value: 0;\n}","folded":true},{"kind":"block","code":"@property --mc203 {\n  syntax: '<integer>';\n  inherits: true;\n  initial-value: 0;\n}","folded":true},{"kind":"block","code":"@property --mc204 {\n  syntax: '<integer>';\n  inherits: true;\n  initial-value: 0;\n}","folded":true},{"kind":"block","code":"@property --mc205 {\n  syntax: '<integer>';\n  inherits: true;\n  initial-value: 0;\n}","folded":true},{"kind":"block","code":"@property --mc206 {\n  syntax: '<integer>';\n  inherits: true;\n  initial-value: 0;\n}","folded":true},{"kind":"block","code":"@property --mc207 {\n  syntax: '<integer>';\n  inherits: true;\n  initial-value: 0;\n}","folded":true},{"kind":"block","code":"@property --mc208 {\n  syntax: '<integer>';\n  inherits: true;\n  initial-value: 0;\n}","folded":true},{"kind":"block","code":"@property --mc209 {\n  syntax: '<integer>';\n  inherits: true;\n  initial-value: 0;\n}","folded":true},{"kind":"block","code":"@property --mc210 {\n  syntax: '<integer>';\n  inherits: true;\n  initial-value: 0;\n}","folded":true},{"kind":"block","code":"@property --mc211 {\n  syntax: '<integer>';\n  inherits: true;\n  initial-value: 0;\n}","folded":true},{"kind":"block","code":"@property --mc212 {\n  syntax: '<integer>';\n  inherits: true;\n  initial-value: 0;\n}","folded":true},{"kind":"block","code":"@property --mc213 {\n  syntax: '<integer>';\n  inherits: true;\n  initial-value: 0;\n}","folded":true},{"kind":"block","code":"@property --mc214 {\n  syntax: '<integer>';\n  inherits: true;\n  initial-value: 0;\n}","folded":true},{"kind":"block","code":"@property --mc215 {\n  syntax: '<integer>';\n  inherits: true;\n  initial-value: 0;\n}","folded":true},{"kind":"block","code":"@property --mc216 {\n  syntax: '<integer>';\n  inherits: true;\n  initial-value: 0;\n}","folded":true},{"kind":"block","code":"@property --mc217 {\n  syntax: '<integer>';\n  inherits: true;\n  initial-value: 0;\n}","folded":true},{"kind":"block","code":"@property --mc218 {\n  syntax: '<integer>';\n  inherits: true;\n  initial-value: 0;\n}","folded":true},{"kind":"block","code":"@property --mc219 {\n  syntax: '<integer>';\n  inherits: true;\n  initial-value: 0;\n}","folded":true},{"kind":"block","code":"@property --mc220 {\n  syntax: '<integer>';\n  inherits: true;\n  initial-value: 0;\n}","folded":true},{"kind":"block","code":"@property --mc221 {\n  syntax: '<integer>';\n  inherits: true;\n  initial-value: 0;\n}","folded":true},{"kind":"block","code":"@property --mc222 {\n  syntax: '<integer>';\n  inherits: true;\n  initial-value: 0;\n}","folded":true},{"kind":"block","code":"@property --mc223 {\n  syntax: '<integer>';\n  inherits: true;\n  initial-value: 0;\n}","folded":true},{"kind":"block","code":"@property --mc224 {\n  syntax: '<integer>';\n  inherits: true;\n  initial-value: 0;\n}","folded":true},{"kind":"block","code":"@property --mc225 {\n  syntax: '<integer>';\n  inherits: true;\n  initial-value: 0;\n}","folded":true},{"kind":"block","code":"@property --mc226 {\n  syntax: '<integer>';\n  inherits: true;\n  initial-value: 0;\n}","folded":true},{"kind":"block","code":"@property --mc227 {\n  syntax: '<integer>';\n  inherits: true;\n  initial-value: 0;\n}","folded":true},{"kind":"block","code":"@property --mc228 {\n  syntax: '<integer>';\n  inherits: true;\n  initial-value: 0;\n}","folded":true},{"kind":"block","code":"@property --mc229 {\n  syntax: '<integer>';\n  inherits: true;\n  initial-value: 0;\n}","folded":true},{"kind":"block","code":"@property --mc230 {\n  syntax: '<integer>';\n  inherits: true;\n  initial-value: 0;\n}","folded":true},{"kind":"block","code":"@property --mc231 {\n  syntax: '<integer>';\n  inherits: true;\n  initial-value: 0;\n}","folded":true},{"kind":"block","code":"@property --mc232 {\n  syntax: '<integer>';\n  inherits: true;\n  initial-value: 0;\n}","folded":true},{"kind":"block","code":"@property --mc233 {\n  syntax: '<integer>';\n  inherits: true;\n  initial-value: 0;\n}","folded":true},{"kind":"block","code":"@property --mc234 {\n  syntax: '<integer>';\n  inherits: true;\n  initial-value: 0;\n}","folded":true},{"kind":"block","code":"@property --mc235 {\n  syntax: '<integer>';\n  inherits: true;\n  initial-value: 0;\n}","folded":true},{"kind":"block","code":"@property --mc236 {\n  syntax: '<integer>';\n  inherits: true;\n  initial-value: 0;\n}","folded":true},{"kind":"block","code":"@property --mc237 {\n  syntax: '<integer>';\n  inherits: true;\n  initial-value: 0;\n}","folded":true},{"kind":"block","code":"@property --mc238 {\n  syntax: '<integer>';\n  inherits: true;\n  initial-value: 0;\n}","folded":true},{"kind":"block","code":"@property --mc239 {\n  syntax: '<integer>';\n  inherits: true;\n  initial-value: 0;\n}","folded":true},{"kind":"block","code":"@property --mc240 {\n  syntax: '<integer>';\n  inherits: true;\n  initial-value: 0;\n}","folded":true},{"kind":"block","code":"@property --mc241 {\n  syntax: '<integer>';\n  inherits: true;\n  initial-value: 0;\n}","folded":true},{"kind":"block","code":"@property --mc242 {\n  syntax: '<integer>';\n  inherits: true;\n  initial-value: 0;\n}","folded":true},{"kind":"block","code":"@property --mc243 {\n  syntax: '<integer>';\n  inherits: true;\n  initial-value: 0;\n}","folded":true},{"kind":"block","code":"@property --mc244 {\n  syntax: '<integer>';\n  inherits: true;\n  initial-value: 0;\n}","folded":true},{"kind":"block","code":"@property --mc245 {\n  syntax: '<integer>';\n  inherits: true;\n  initial-value: 0;\n}","folded":true},{"kind":"block","code":"@property --mc246 {\n  syntax: '<integer>';\n  inherits: true;\n  initial-value: 0;\n}","folded":true},{"kind":"block","code":"@property --mc247 {\n  syntax: '<integer>';\n  inherits: true;\n  initial-value: 0;\n}","folded":true},{"kind":"block","code":"@property --mc248 {\n  syntax: '<integer>';\n  inherits: true;\n  initial-value: 0;\n}","folded":true},{"kind":"block","code":"@property --mc249 {\n  syntax: '<integer>';\n  inherits: true;\n  initial-value: 0;\n}","folded":true},{"kind":"block","code":"@property --mc250 {\n  syntax: '<integer>';\n  inherits: true;\n  initial-value: 0;\n}","folded":true},{"kind":"block","code":"@property --mc251 {\n  syntax: '<integer>';\n  inherits: true;\n  initial-value: 0;\n}","folded":true},{"kind":"block","code":"@property --mc252 {\n  syntax: '<integer>';\n  inherits: true;\n  initial-value: 0;\n}","folded":true},{"kind":"block","code":"@property --mc253 {\n  syntax: '<integer>';\n  inherits: true;\n  initial-value: 0;\n}","folded":true},{"kind":"block","code":"@property --mc254 {\n  syntax: '<integer>';\n  inherits: true;\n  initial-value: 0;\n}","folded":true},{"kind":"block","code":"@property --mc255 {\n  syntax: '<integer>';\n  inherits: true;\n  initial-value: 0;\n}","folded":true},{"kind":"block","code":"@property --mc256 {\n  syntax: '<integer>';\n  inherits: true;\n  initial-value: 0;\n}","folded":true},{"kind":"block","code":"@property --mc257 {\n  syntax: '<integer>';\n  inherits: true;\n  initial-value: 0;\n}","folded":true},{"kind":"block","code":"@property --mc258 {\n  syntax: '<integer>';\n  inherits: true;\n  initial-value: 0;\n}","folded":true},{"kind":"block","code":"@property --mc259 {\n  syntax: '<integer>';\n  inherits: true;\n  initial-value: 0;\n}","folded":true},{"kind":"block","code":"@property --mc260 {\n  syntax: '<integer>';\n  inherits: true;\n  initial-value: 0;\n}","folded":true},{"kind":"block","code":"@property --mc261 {\n  syntax: '<integer>';\n  inherits: true;\n  initial-value: 0;\n}","folded":true},{"kind":"block","code":"@property --mc262 {\n  syntax: '<integer>';\n  inherits: true;\n  initial-value: 0;\n}","folded":true},{"kind":"block","code":"@property --mc263 {\n  syntax: '<integer>';\n  inherits: true;\n  initial-value: 0;\n}","folded":true},{"kind":"block","code":"@property --mc264 {\n  syntax: '<integer>';\n  inherits: true;\n  initial-value: 0;\n}","folded":true},{"kind":"block","code":"@property --mc265 {\n  syntax: '<integer>';\n  inherits: true;\n  initial-value: 0;\n}","folded":true},{"kind":"block","code":"@property --mc266 {\n  syntax: '<integer>';\n  inherits: true;\n  initial-value: 0;\n}","folded":true},{"kind":"block","code":"@property --mc267 {\n  syntax: '<integer>';\n  inherits: true;\n  initial-value: 0;\n}","folded":true},{"kind":"block","code":"@property --mc268 {\n  syntax: '<integer>';\n  inherits: true;\n  initial-value: 0;\n}","folded":true},{"kind":"block","code":"@property --mc269 {\n  syntax: '<integer>';\n  inherits: true;\n  initial-value: 0;\n}","folded":true},{"kind":"block","code":"@property --mc270 {\n  syntax: '<integer>';\n  inherits: true;\n  initial-value: 0;\n}","folded":true},{"kind":"block","code":"@property --mc271 {\n  syntax: '<integer>';\n  inherits: true;\n  initial-value: 0;\n}","folded":true},{"kind":"block","code":"@property --mc272 {\n  syntax: '<integer>';\n  inherits: true;\n  initial-value: 0;\n}","folded":true},{"kind":"block","code":"@property --mc273 {\n  syntax: '<integer>';\n  inherits: true;\n  initial-value: 0;\n}","folded":true},{"kind":"block","code":"@property --mc274 {\n  syntax: '<integer>';\n  inherits: true;\n  initial-value: 0;\n}","folded":true},{"kind":"block","code":"@property --mc275 {\n  syntax: '<integer>';\n  inherits: true;\n  initial-value: 0;\n}","folded":true},{"kind":"block","code":"@property --mc276 {\n  syntax: '<integer>';\n  inherits: true;\n  initial-value: 0;\n}","folded":true},{"kind":"block","code":"@property --mc277 {\n  syntax: '<integer>';\n  inherits: true;\n  initial-value: 0;\n}","folded":true},{"kind":"block","code":"@property --mc278 {\n  syntax: '<integer>';\n  inherits: true;\n  initial-value: 0;\n}","folded":true},{"kind":"block","code":"@property --mc279 {\n  syntax: '<integer>';\n  inherits: true;\n  initial-value: 0;\n}","folded":true},{"kind":"block","code":"@property --mc280 {\n  syntax: '<integer>';\n  inherits: true;\n  initial-value: 0;\n}","folded":true},{"kind":"block","code":"@property --mc281 {\n  syntax: '<integer>';\n  inherits: true;\n  initial-value: 0;\n}","folded":true},{"kind":"block","code":"@property --mc282 {\n  syntax: '<integer>';\n  inherits: true;\n  initial-value: 0;\n}","folded":true},{"kind":"block","code":"@property --mc283 {\n  syntax: '<integer>';\n  inherits: true;\n  initial-value: 0;\n}","folded":true},{"kind":"block","code":"@property --mc284 {\n  syntax: '<integer>';\n  inherits: true;\n  initial-value: 0;\n}","folded":true},{"kind":"block","code":"@property --mc285 {\n  syntax: '<integer>';\n  inherits: true;\n  initial-value: 0;\n}","folded":true},{"kind":"block","code":"@property --mc286 {\n  syntax: '<integer>';\n  inherits: true;\n  initial-value: 0;\n}","folded":true},{"kind":"block","code":"@property --mc287 {\n  syntax: '<integer>';\n  inherits: true;\n  initial-value: 0;\n}","folded":true},{"kind":"block","code":"@property --mc288 {\n  syntax: '<integer>';\n  inherits: true;\n  initial-value: 0;\n}","folded":true},{"kind":"block","code":"@property --mc289 {\n  syntax: '<integer>';\n  inherits: true;\n  initial-value: 0;\n}","folded":true},{"kind":"block","code":"@property --mc290 {\n  syntax: '<integer>';\n  inherits: true;\n  initial-value: 0;\n}","folded":true},{"kind":"block","code":"@property --mc291 {\n  syntax: '<integer>';\n  inherits: true;\n  initial-value: 0;\n}","folded":true},{"kind":"block","code":"@property --mc292 {\n  syntax: '<integer>';\n  inherits: true;\n  initial-value: 0;\n}","folded":true},{"kind":"block","code":"@property --mc293 {\n  syntax: '<integer>';\n  inherits: true;\n  initial-value: 0;\n}","folded":true},{"kind":"block","code":"@property --mc294 {\n  syntax: '<integer>';\n  inherits: true;\n  initial-value: 0;\n}","folded":true},{"kind":"block","code":"@property --mc295 {\n  syntax: '<integer>';\n  inherits: true;\n  initial-value: 0;\n}","folded":true},{"kind":"block","code":"@property --mc296 {\n  syntax: '<integer>';\n  inherits: true;\n  initial-value: 0;\n}","folded":true},{"kind":"block","code":"@property --mc297 {\n  syntax: '<integer>';\n  inherits: true;\n  initial-value: 0;\n}","folded":true},{"kind":"block","code":"@property --mc298 {\n  syntax: '<integer>';\n  inherits: true;\n  initial-value: 0;\n}","folded":true},{"kind":"block","code":"@property --mc299 {\n  syntax: '<integer>';\n  inherits: true;\n  initial-value: 0;\n}","folded":true},{"kind":"block","code":"@property --mc300 {\n  syntax: '<integer>';\n  inherits: true;\n  initial-value: 0;\n}","folded":true},{"kind":"block","code":"@property --mc301 {\n  syntax: '<integer>';\n  inherits: true;\n  initial-value: 0;\n}","folded":true},{"kind":"block","code":"@property --mc302 {\n  syntax: '<integer>';\n  inherits: true;\n  initial-value: 0;\n}","folded":true},{"kind":"block","code":"@property --mc303 {\n  syntax: '<integer>';\n  inherits: true;\n  initial-value: 0;\n}","folded":true},{"kind":"block","code":"@property --mc304 {\n  syntax: '<integer>';\n  inherits: true;\n  initial-value: 0;\n}","folded":true},{"kind":"block","code":"@property --mc305 {\n  syntax: '<integer>';\n  inherits: true;\n  initial-value: 0;\n}","folded":true},{"kind":"block","code":"@property --mc306 {\n  syntax: '<integer>';\n  inherits: true;\n  initial-value: 0;\n}","folded":true},{"kind":"block","code":"@property --mc307 {\n  syntax: '<integer>';\n  inherits: true;\n  initial-value: 0;\n}","folded":true},{"kind":"block","code":"@property --mc308 {\n  syntax: '<integer>';\n  inherits: true;\n  initial-value: 0;\n}","folded":true},{"kind":"block","code":"@property --mc309 {\n  syntax: '<integer>';\n  inherits: true;\n  initial-value: 0;\n}","folded":true},{"kind":"block","code":"@property --mc310 {\n  syntax: '<integer>';\n  inherits: true;\n  initial-value: 0;\n}","folded":true},{"kind":"block","code":"@property --mc311 {\n  syntax: '<integer>';\n  inherits: true;\n  initial-value: 0;\n}","folded":true},{"kind":"block","code":"@property --mc312 {\n  syntax: '<integer>';\n  inherits: true;\n  initial-value: 0;\n}","folded":true},{"kind":"block","code":"@property --mc313 {\n  syntax: '<integer>';\n  inherits: true;\n  initial-value: 0;\n}","folded":true},{"kind":"block","code":"@property --mc314 {\n  syntax: '<integer>';\n  inherits: true;\n  initial-value: 0;\n}","folded":true},{"kind":"block","code":"@property --mc315 {\n  syntax: '<integer>';\n  inherits: true;\n  initial-value: 0;\n}","folded":true},{"kind":"block","code":"@property --mc316 {\n  syntax: '<integer>';\n  inherits: true;\n  initial-value: 0;\n}","folded":true},{"kind":"block","code":"@property --mc317 {\n  syntax: '<integer>';\n  inherits: true;\n  initial-value: 0;\n}","folded":true},{"kind":"block","code":"@property --mc318 {\n  syntax: '<integer>';\n  inherits: true;\n  initial-value: 0;\n}","folded":true},{"kind":"block","code":"@property --mc319 {\n  syntax: '<integer>';\n  inherits: true;\n  initial-value: 0;\n}","folded":true},{"kind":"block","code":"@property --mc320 {\n  syntax: '<integer>';\n  inherits: true;\n  initial-value: 0;\n}","folded":true},{"kind":"block","code":"@property --mc321 {\n  syntax: '<integer>';\n  inherits: true;\n  initial-value: 0;\n}","folded":true},{"kind":"block","code":"@property --mc322 {\n  syntax: '<integer>';\n  inherits: true;\n  initial-value: 0;\n}","folded":true},{"kind":"block","code":"@property --mc323 {\n  syntax: '<integer>';\n  inherits: true;\n  initial-value: 0;\n}","folded":true},{"kind":"block","code":"@property --mc324 {\n  syntax: '<integer>';\n  inherits: true;\n  initial-value: 0;\n}","folded":true},{"kind":"block","code":"@property --mc325 {\n  syntax: '<integer>';\n  inherits: true;\n  initial-value: 0;\n}","folded":true},{"kind":"block","code":"@property --mc326 {\n  syntax: '<integer>';\n  inherits: true;\n  initial-value: 0;\n}","folded":true},{"kind":"block","code":"@property --mc327 {\n  syntax: '<integer>';\n  inherits: true;\n  initial-value: 0;\n}","folded":true},{"kind":"block","code":"@property --mc328 {\n  syntax: '<integer>';\n  inherits: true;\n  initial-value: 0;\n}","folded":true},{"kind":"block","code":"@property --mc329 {\n  syntax: '<integer>';\n  inherits: true;\n  initial-value: 0;\n}","folded":true}],"next":{"ref":"decl/001","remaining":444}}